{
  "updated_at": "2026-02-02T15:42:01.516Z",
  "count": 80,
  "events": [
    {
      "id": "139e6f65db9aa4a1c87ea287dd2dc19644f4ee6b",
      "title": "LP And The Vinyl",
      "description": "After years of intensive recording projects and concerts for jazz aficionados throughout the U.S., four San Diegobased musicians came together with a purpose: explore the art of song in their own unique way! Renowned jazz, blues and gospel singer Leonard Patton teamed up with the critically acclaimed Danny Green Trio to form LP And The Vinyl. The band?s wide array of influences includes everything from jazz, R&B, and rock, to 80?s and 90?s hits, Brazilian music, and classical music. Blending these sounds together, LP And The Vinyl has created a highly unique and personal approach to music-making that leaves its audiences energized and craving more. The group?s repertoire draws from three separate areas: beautifully reimagined renditions of favorite hits by artists including Stevie Wonder, The Beatles, and David Bowie, fresh and funky explorations of jazz standards, and their own original songs.",
      "start_datetime": "2026-02-06T01:00:00.000Z",
      "end_datetime": null,
      "venue": {
        "name": "The Carolina",
        "address": "Carolina Theatre Charlotte Belk Place - 230 North Tryon",
        "neighborhood": "",
        "lat": 35.22827319,
        "lng": -80.84086174
      },
      "category": [
        "concert",
        "nightlife"
      ],
      "price": {
        "min": null,
        "max": null,
        "currency": "USD",
        "notes": "See website"
      },
      "image": "https://s1.ticketm.net/dam/a/a76/95bbd6ee-c3c8-4d72-a7d2-7db1f1860a76_1422171_RETINA_PORTRAIT_16_9.jpg",
      "source": {
        "name": "Ticketmaster API",
        "url": "https://app.ticketmaster.com/discovery/v2/events",
        "scraped_at": "2026-02-02T15:42:01.511Z"
      },
      "url": "https://www.ticketmaster.com/lp-and-the-vinyl-charlotte-north-carolina-02-05-2026/event/2D00635CCF07C7B3",
      "confidence": 1,
      "tags": [
        "ticketmaster-api",
        "music"
      ],
      "_rank_score": 85
    },
    {
      "id": "4bfaaec575bc3e68fb6a5054020aecf3a2dfe0f5",
      "title": "112 - Room 112 Tour",
      "description": "Doors 7:00pm. Show 8:00pm.",
      "start_datetime": "2026-02-06T01:00:00.000Z",
      "end_datetime": null,
      "venue": {
        "name": "Ovens Auditorium",
        "address": "2900 E Independence Boulevard",
        "neighborhood": "East Charlotte",
        "lat": 35.2050931,
        "lng": -80.7953024
      },
      "category": [
        "concert",
        "nightlife"
      ],
      "price": {
        "min": null,
        "max": null,
        "currency": "USD",
        "notes": "See website"
      },
      "image": "https://s1.ticketm.net/dam/a/018/369fc50a-d7c5-4235-8d6a-297771066018_1070171_TABLET_LANDSCAPE_16_9.jpg",
      "source": {
        "name": "Ticketmaster API",
        "url": "https://app.ticketmaster.com/discovery/v2/events",
        "scraped_at": "2026-02-02T15:42:01.511Z"
      },
      "url": "https://www.ticketmaster.com/112-room-112-tour-charlotte-north-carolina-02-05-2026/event/2D006314E6ACB3D5",
      "confidence": 1,
      "tags": [
        "ticketmaster-api",
        "music"
      ],
      "_rank_score": 85
    },
    {
      "id": "a51056ee989226e1e17f6f83a5163a41847bbed7",
      "title": "Langhorne Slim: The Dreamin' Kind Tour",
      "description": "Age Policy: 18+ Valid ID required for entry into venue / Under 18 permitted with parent (Accepted forms of ID: State Issued ID or Driver's License, Military ID, Passport.) *DELAYED DELIVERY: Tickets will be emailed 5 days before the show.*",
      "start_datetime": "2026-02-07T01:00:00.000Z",
      "end_datetime": null,
      "venue": {
        "name": "Neighborhood Theatre Main Room",
        "address": "511 E 36th St",
        "neighborhood": "",
        "lat": 35.247447,
        "lng": -80.803888
      },
      "category": [
        "concert",
        "nightlife"
      ],
      "price": {
        "min": null,
        "max": null,
        "currency": "USD",
        "notes": "See website"
      },
      "image": "https://s1.ticketm.net/dam/e/e55/d151bd90-afcc-42c1-a221-43f8ff82ee55_TABLET_LANDSCAPE_LARGE_16_9.jpg",
      "source": {
        "name": "Ticketmaster API",
        "url": "https://app.ticketmaster.com/discovery/v2/events",
        "scraped_at": "2026-02-02T15:42:01.511Z"
      },
      "url": "https://www.ticketmaster.com/langhorne-slim-the-dreamin-kind-tour-charlotte-north-carolina-02-06-2026/event/2D00636BBE5FD807",
      "confidence": 1,
      "tags": [
        "ticketmaster-api",
        "music"
      ],
      "_rank_score": 85
    },
    {
      "id": "14d9ff984a0c503a306706993babfaba01077bff",
      "title": "MC DAVO & SABINO",
      "description": "The Underground Is A General Admission Standing Room Only Venue Unless Otherwise Noted. All Ages Welcome Doors: 7:00pm Show: 8:00pm Ticket prices will increase the day of the show. All dates, acts, and ticket prices subject to change without notice. All tickets are subject to applicable service fees via all points of purchase.",
      "start_datetime": "2026-02-07T01:00:00.000Z",
      "end_datetime": null,
      "venue": {
        "name": "The Underground",
        "address": "820 Hamilton St",
        "neighborhood": "",
        "lat": 35.240299,
        "lng": -80.845314
      },
      "category": [
        "concert",
        "nightlife"
      ],
      "price": {
        "min": null,
        "max": null,
        "currency": "USD",
        "notes": "See website"
      },
      "image": "https://s1.ticketm.net/dam/a/ac7/c3292054-79a4-4f3b-afd4-e74246d31ac7_TABLET_LANDSCAPE_16_9.jpg",
      "source": {
        "name": "Ticketmaster API",
        "url": "https://app.ticketmaster.com/discovery/v2/events",
        "scraped_at": "2026-02-02T15:42:01.511Z"
      },
      "url": "https://www.ticketmaster.com/mc-davo-sabino-charlotte-north-carolina-02-06-2026/event/2D00635F992A7D5A",
      "confidence": 1,
      "tags": [
        "ticketmaster-api",
        "music"
      ],
      "_rank_score": 85
    },
    {
      "id": "d1e11ff694e7308f4c43f5c3d55bd7ddc7b8a456",
      "title": "Ricardo Arjona - LO QUE EL SECO NO DIJO TOUR",
      "description": "Ricardo Arjona - LO QUE EL SECO NO DIJO TOUR at Spectrum Center",
      "start_datetime": "2026-02-04T01:00:00.000Z",
      "end_datetime": null,
      "venue": {
        "name": "Spectrum Center",
        "address": "333 East Trade Street",
        "neighborhood": "Uptown",
        "lat": 35.225222,
        "lng": -80.839921
      },
      "category": [
        "concert",
        "nightlife"
      ],
      "price": {
        "min": null,
        "max": null,
        "currency": "USD",
        "notes": "See website"
      },
      "image": "https://s1.ticketm.net/dam/a/0b9/8f1157e7-33a2-4285-83e5-d2bf0719b0b9_TABLET_LANDSCAPE_16_9.jpg",
      "source": {
        "name": "Ticketmaster API",
        "url": "https://app.ticketmaster.com/discovery/v2/events",
        "scraped_at": "2026-02-02T15:42:01.511Z"
      },
      "url": "https://www.ticketmaster.com/ricardo-arjona-lo-que-el-seco-charlotte-north-carolina-02-03-2026/event/2D006324A1939D40",
      "confidence": 1,
      "tags": [
        "ticketmaster-api",
        "music"
      ],
      "_rank_score": 80
    },
    {
      "id": "07bd3ccaaa78cef329713e1cd2ef0ba699426988",
      "title": "The Wombats: Oh! The Ocean Tour",
      "description": "The Fillmore Is A General Admission Standing Room Only Venue Unless Otherwise Noted. All Ages Welcome Doors: 7:00PM Show: 8:00PM Ticket prices will increase the day of the show. All dates, acts, and ticket prices subject to change without notice. All tickets are subject to applicable service fees via all points of purchase.",
      "start_datetime": "2026-02-05T01:00:00.000Z",
      "end_datetime": null,
      "venue": {
        "name": "The Fillmore Charlotte",
        "address": "820 Hamilton Street",
        "neighborhood": "",
        "lat": 35.239095,
        "lng": -80.845519
      },
      "category": [
        "concert",
        "nightlife"
      ],
      "price": {
        "min": null,
        "max": null,
        "currency": "USD",
        "notes": "See website"
      },
      "image": "https://s1.ticketm.net/dam/a/25a/f4b64033-18cf-49b1-98db-e0c7b5afe25a_TABLET_LANDSCAPE_16_9.jpg",
      "source": {
        "name": "Ticketmaster API",
        "url": "https://app.ticketmaster.com/discovery/v2/events",
        "scraped_at": "2026-02-02T15:42:01.511Z"
      },
      "url": "https://www.ticketmaster.com/the-wombats-oh-the-ocean-tour-charlotte-north-carolina-02-04-2026/event/2D006365E37FEDB0",
      "confidence": 1,
      "tags": [
        "ticketmaster-api",
        "music"
      ],
      "_rank_score": 80
    },
    {
      "id": "aa14dcdc7f7546a7bcfde9a4eeca930a4a8cca4e",
      "title": "K-WINTERLAND: K-pop Dance Party (18+)",
      "description": "Age Policy: 18+ Valid ID required for entry into venue (Accepted forms of ID: State Issued ID or Driver's License, Military ID, Passport.)",
      "start_datetime": "2026-02-08T01:00:00.000Z",
      "end_datetime": null,
      "venue": {
        "name": "Neighborhood Theatre Tap Room",
        "address": "511 E 36th St, Charlotte",
        "neighborhood": "",
        "lat": 35.24779,
        "lng": -80.0403
      },
      "category": [
        "concert",
        "nightlife"
      ],
      "price": {
        "min": null,
        "max": null,
        "currency": "USD",
        "notes": "See website"
      },
      "image": "https://s1.ticketm.net/dam/e/a39/2834f92b-dc16-4cb3-838b-67e5d4b68a39_TABLET_LANDSCAPE_LARGE_16_9.jpg",
      "source": {
        "name": "Ticketmaster API",
        "url": "https://app.ticketmaster.com/discovery/v2/events",
        "scraped_at": "2026-02-02T15:42:01.511Z"
      },
      "url": "https://www.ticketmaster.com/kwinterland-kpop-dance-party-18-charlotte-north-carolina-02-07-2026/event/2D006365F2BCFAE8",
      "confidence": 1,
      "tags": [
        "ticketmaster-api",
        "music"
      ],
      "_rank_score": 75
    },
    {
      "id": "342a6bdf03706349e0448174f72a3e4f1b970927",
      "title": "Hot In Herre: 2000s Dance Party (18+)",
      "description": "The Underground Is A General Admission Standing Room Only Venue Unless Otherwise Noted. Ages 18+ Welcome Doors: 8:00pm Show: 9:00pm Ticket prices will increase the day of the show. All dates, acts, and ticket prices subject to change without notice. All tickets are subject to applicable service fees via all points of purchase.",
      "start_datetime": "2026-02-08T02:00:00.000Z",
      "end_datetime": null,
      "venue": {
        "name": "The Underground",
        "address": "820 Hamilton St",
        "neighborhood": "",
        "lat": 35.240299,
        "lng": -80.845314
      },
      "category": [
        "concert",
        "nightlife"
      ],
      "price": {
        "min": null,
        "max": null,
        "currency": "USD",
        "notes": "See website"
      },
      "image": "https://s1.ticketm.net/dam/a/a28/e5db7882-f195-430e-b053-7c8dcc3a5a28_TABLET_LANDSCAPE_16_9.jpg",
      "source": {
        "name": "Ticketmaster API",
        "url": "https://app.ticketmaster.com/discovery/v2/events",
        "scraped_at": "2026-02-02T15:42:01.511Z"
      },
      "url": "https://www.ticketmaster.com/hot-in-herre-2000s-dance-party-charlotte-north-carolina-02-07-2026/event/2D0063792E01F190",
      "confidence": 1,
      "tags": [
        "ticketmaster-api",
        "music"
      ],
      "_rank_score": 75
    },
    {
      "id": "a62292a716224dd974d773ef3087018f6e9dabae",
      "title": "Opiuo (18+)",
      "description": "Opiuo (18+) at Blackbox Theater - Charlotte",
      "start_datetime": "2026-02-08T03:00:00.000Z",
      "end_datetime": null,
      "venue": {
        "name": "Blackbox Theater - Charlotte",
        "address": "421 East Sugar Creek Rd",
        "neighborhood": "",
        "lat": 35.2897,
        "lng": -80.730202
      },
      "category": [
        "concert",
        "nightlife"
      ],
      "price": {
        "min": null,
        "max": null,
        "currency": "USD",
        "notes": "See website"
      },
      "image": "https://s1.ticketm.net/dam/a/d70/3210a14c-8bb7-49a0-aa8b-e6b384e64d70_176701_RETINA_PORTRAIT_3_2.jpg",
      "source": {
        "name": "Ticketmaster API",
        "url": "https://app.ticketmaster.com/discovery/v2/events",
        "scraped_at": "2026-02-02T15:42:01.511Z"
      },
      "url": "https://www.ticketmaster.com/event/Z7r9jZ1A7r4_N",
      "confidence": 1,
      "tags": [
        "ticketmaster-api",
        "music"
      ],
      "_rank_score": 75
    },
    {
      "id": "94165cde1ea930c2b8a82e22290eddb4ea745ddf",
      "title": "Eric Neumann",
      "description": "Eric Neumann at Comedy Zone - Charlotte",
      "start_datetime": "2026-02-13T00:00:00.000Z",
      "end_datetime": null,
      "venue": {
        "name": "Comedy Zone - Charlotte",
        "address": "900 NC Music Factory Blvd B3",
        "neighborhood": "",
        "lat": 35.256302,
        "lng": -80.821198
      },
      "category": [
        "concert",
        "nightlife"
      ],
      "price": {
        "min": null,
        "max": null,
        "currency": "USD",
        "notes": "See website"
      },
      "image": "https://s1.ticketm.net/dam/c/060/c5c08e7a-9912-456c-a060-2758be94e060_105881_RETINA_PORTRAIT_3_2.jpg",
      "source": {
        "name": "Ticketmaster API",
        "url": "https://app.ticketmaster.com/discovery/v2/events",
        "scraped_at": "2026-02-02T15:42:01.512Z"
      },
      "url": "https://www.ticketmaster.com/event/Z7r9jZ1A7qSFP",
      "confidence": 1,
      "tags": [
        "ticketmaster-api",
        "music"
      ],
      "_rank_score": 75
    },
    {
      "id": "ceba7acbe29ce87ac6970f3448cf3e80e27fea8f",
      "title": "MOLOTOV - 30TH ANNIVERSARY TXXXR",
      "description": "Doors 7pm. Show 8pm.",
      "start_datetime": "2026-02-13T01:00:00.000Z",
      "end_datetime": null,
      "venue": {
        "name": "Ovens Auditorium",
        "address": "2900 E Independence Boulevard",
        "neighborhood": "East Charlotte",
        "lat": 35.2050931,
        "lng": -80.7953024
      },
      "category": [
        "concert",
        "nightlife"
      ],
      "price": {
        "min": null,
        "max": null,
        "currency": "USD",
        "notes": "See website"
      },
      "image": "https://s1.ticketm.net/dam/a/be3/f66e87fb-0ff4-4e50-b849-2f2cf654fbe3_743281_TABLET_LANDSCAPE_LARGE_16_9.jpg",
      "source": {
        "name": "Ticketmaster API",
        "url": "https://app.ticketmaster.com/discovery/v2/events",
        "scraped_at": "2026-02-02T15:42:01.512Z"
      },
      "url": "https://www.ticketmaster.com/molotov-30th-anniversary-txxxr-charlotte-north-carolina-02-12-2026/event/2D006341B9F756B8",
      "confidence": 1,
      "tags": [
        "ticketmaster-api",
        "music"
      ],
      "_rank_score": 75
    },
    {
      "id": "fcf8656beac15a271648b02a87ffed0e1ae7c04f",
      "title": "Drew and Ellie Holcomb - Never Gonna Let You Go Tour",
      "description": "Drew and Ellie Holcomb - Never Gonna Let You Go Tour at Knight Theater",
      "start_datetime": "2026-02-13T01:00:00.000Z",
      "end_datetime": null,
      "venue": {
        "name": "Knight Theater",
        "address": "430 South Tryon St",
        "neighborhood": "Uptown",
        "lat": 35.2242679,
        "lng": -80.8473758
      },
      "category": [
        "concert",
        "nightlife"
      ],
      "price": {
        "min": null,
        "max": null,
        "currency": "USD",
        "notes": "See website"
      },
      "image": "https://s1.ticketm.net/dam/a/64a/5e8d97d4-8f89-4d35-91c0-e5ab9203164a_RETINA_LANDSCAPE_16_9.jpg",
      "source": {
        "name": "Ticketmaster API",
        "url": "https://app.ticketmaster.com/discovery/v2/events",
        "scraped_at": "2026-02-02T15:42:01.512Z"
      },
      "url": "https://tix.blumenthalarts.org/online/default.asp?doWork::WScontent::loadArticle=Load&BOparam::WScontent::loadArticle::article_id=97414893-E65C-4A38-9DD6-251BC442B868",
      "confidence": 1,
      "tags": [
        "ticketmaster-api",
        "music"
      ],
      "_rank_score": 75
    },
    {
      "id": "fb6e4277dc69e664eca0756b4f8a499ea28eeea6",
      "title": "Drew and Ellie Holcomb",
      "description": "Drew and Ellie Holcomb at Knight Theater",
      "start_datetime": "2026-02-13T01:00:00.000Z",
      "end_datetime": null,
      "venue": {
        "name": "Knight Theater",
        "address": "430 South Tryon St.",
        "neighborhood": "Uptown",
        "lat": 35.228001,
        "lng": -80.844597
      },
      "category": [
        "concert",
        "nightlife"
      ],
      "price": {
        "min": null,
        "max": null,
        "currency": "USD",
        "notes": "See website"
      },
      "image": "https://s1.ticketm.net/dam/a/64a/5e8d97d4-8f89-4d35-91c0-e5ab9203164a_RETINA_LANDSCAPE_16_9.jpg",
      "source": {
        "name": "Ticketmaster API",
        "url": "https://app.ticketmaster.com/discovery/v2/events",
        "scraped_at": "2026-02-02T15:42:01.512Z"
      },
      "url": "https://www.ticketmaster.com/event/Z7r9jZ1A7_SZ-",
      "confidence": 1,
      "tags": [
        "ticketmaster-api",
        "music"
      ],
      "_rank_score": 75
    },
    {
      "id": "08e5233b99150c34fc78977cfc2db7ba66e06168",
      "title": "The Queens: 4 Legends, 1 Stage",
      "description": "The Queens: 4 Legends, 1 Stage at Spectrum Center",
      "start_datetime": "2026-02-14T01:00:00.000Z",
      "end_datetime": null,
      "venue": {
        "name": "Spectrum Center",
        "address": "333 East Trade Street",
        "neighborhood": "Uptown",
        "lat": 35.225222,
        "lng": -80.839921
      },
      "category": [
        "concert",
        "nightlife"
      ],
      "price": {
        "min": null,
        "max": null,
        "currency": "USD",
        "notes": "See website"
      },
      "image": "https://s1.ticketm.net/dam/a/f3f/d4f90e5a-d9bb-472f-ae05-c7edec30df3f_SOURCE",
      "source": {
        "name": "Ticketmaster API",
        "url": "https://app.ticketmaster.com/discovery/v2/events",
        "scraped_at": "2026-02-02T15:42:01.512Z"
      },
      "url": "https://www.ticketmaster.com/the-queens-4-legends-1-stage-charlotte-north-carolina-02-13-2026/event/2D0063679DD8C7D7",
      "confidence": 1,
      "tags": [
        "ticketmaster-api",
        "music"
      ],
      "_rank_score": 75
    },
    {
      "id": "fe957d718545d17254bb6990f9bda4bd2f6dd1c0",
      "title": "Gimme Gimme Disco (18+)",
      "description": "Age Policy: 18+ Valid ID required for entry into venue (Accepted forms of ID: State Issued ID or Driver's License, Military ID, Passport.)",
      "start_datetime": "2026-02-14T01:30:00.000Z",
      "end_datetime": null,
      "venue": {
        "name": "Neighborhood Theatre Main Room",
        "address": "511 E 36th St",
        "neighborhood": "",
        "lat": 35.247447,
        "lng": -80.803888
      },
      "category": [
        "concert",
        "nightlife"
      ],
      "price": {
        "min": null,
        "max": null,
        "currency": "USD",
        "notes": "See website"
      },
      "image": "https://s1.ticketm.net/dam/e/fdc/afd52889-23f7-4c4b-9d5a-0225e0fe3fdc_TABLET_LANDSCAPE_3_2.jpg",
      "source": {
        "name": "Ticketmaster API",
        "url": "https://app.ticketmaster.com/discovery/v2/events",
        "scraped_at": "2026-02-02T15:42:01.512Z"
      },
      "url": "https://www.ticketmaster.com/gimme-gimme-disco-18-charlotte-north-carolina-02-13-2026/event/2D006426322BFB8E",
      "confidence": 1,
      "tags": [
        "ticketmaster-api",
        "music"
      ],
      "_rank_score": 75
    },
    {
      "id": "3a4d451c51e91b0d91cc93bd9414538f8dedc394",
      "title": "Justin Bieber Night: Presented By Stan Society (18+)",
      "description": "The Underground Is A General Admission Standing Room Only Venue Unless Otherwise Noted. Ages 18+ Welcome Doors: 8:30PM Show: 9:00PM Ticket prices will increase the day of the show. All dates, acts, and ticket prices subject to change without notice. All tickets are subject to applicable service fees via all points of purchase.",
      "start_datetime": "2026-02-14T02:00:00.000Z",
      "end_datetime": null,
      "venue": {
        "name": "The Underground",
        "address": "820 Hamilton St",
        "neighborhood": "",
        "lat": 35.240299,
        "lng": -80.845314
      },
      "category": [
        "concert",
        "nightlife"
      ],
      "price": {
        "min": null,
        "max": null,
        "currency": "USD",
        "notes": "See website"
      },
      "image": "https://s1.ticketm.net/dam/e/504/5ea9f138-e2c2-4347-9485-a724f173e504_RETINA_PORTRAIT_16_9.jpg",
      "source": {
        "name": "Ticketmaster API",
        "url": "https://app.ticketmaster.com/discovery/v2/events",
        "scraped_at": "2026-02-02T15:42:01.512Z"
      },
      "url": "https://www.ticketmaster.com/justin-bieber-night-presented-by-stan-charlotte-north-carolina-02-13-2026/event/2D006390A79994DF",
      "confidence": 1,
      "tags": [
        "ticketmaster-api",
        "music"
      ],
      "_rank_score": 75
    },
    {
      "id": "91a0448609ccc1f27330681a67551fc4731bdbba",
      "title": "Ian Munsick",
      "description": "Ian Munsick at Coyote Joes",
      "start_datetime": "2026-02-14T04:00:00.000Z",
      "end_datetime": null,
      "venue": {
        "name": "Coyote Joes",
        "address": "4621 Wilkinson Blvd.",
        "neighborhood": "",
        "lat": 35.221001,
        "lng": -80.927597
      },
      "category": [
        "concert",
        "nightlife"
      ],
      "price": {
        "min": null,
        "max": null,
        "currency": "USD",
        "notes": "See website"
      },
      "image": "https://s1.ticketm.net/dam/a/98c/970082db-8334-42e0-aa4a-2241ae05f98c_TABLET_LANDSCAPE_LARGE_16_9.jpg",
      "source": {
        "name": "Ticketmaster API",
        "url": "https://app.ticketmaster.com/discovery/v2/events",
        "scraped_at": "2026-02-02T15:42:01.512Z"
      },
      "url": "https://www.ticketmaster.com/event/Z7r9jZ1A7q7P8",
      "confidence": 1,
      "tags": [
        "ticketmaster-api",
        "music"
      ],
      "_rank_score": 75
    },
    {
      "id": "62ac3b72adb3901764caf849dfc0b471b75de576",
      "title": "Charlotte Checkers vs. Grand Rapids Griffins",
      "description": "BAG POLICY: Any non-clear bag larger than 4.5\" x 6.5\" is not permitted.",
      "start_datetime": "2026-02-07T00:00:00.000Z",
      "end_datetime": null,
      "venue": {
        "name": "Bojangles Coliseum",
        "address": "2700 E Independence Boulevard",
        "neighborhood": "East Charlotte",
        "lat": 35.2050931,
        "lng": -80.7953024
      },
      "category": [
        "sports"
      ],
      "price": {
        "min": null,
        "max": null,
        "currency": "USD",
        "notes": "See website"
      },
      "image": "https://s1.ticketm.net/dam/a/8d9/818ee4bb-df3e-4d58-8468-c23e293418d9_851601_RETINA_PORTRAIT_16_9.jpg",
      "source": {
        "name": "Ticketmaster API",
        "url": "https://app.ticketmaster.com/discovery/v2/events",
        "scraped_at": "2026-02-02T15:42:01.511Z"
      },
      "url": "https://www.ticketmaster.com/charlotte-checkers-vs-grand-rapids-griffins-charlotte-north-carolina-02-06-2026/event/2D00631AE65E623F",
      "confidence": 1,
      "tags": [
        "ticketmaster-api",
        "sports"
      ],
      "_rank_score": 65
    },
    {
      "id": "9d20f0458cf31eec4e3da15a0d27a774fd18ff87",
      "title": "WWE Friday Night SmackDown",
      "description": "WWE Friday Night SmackDown at Spectrum Center",
      "start_datetime": "2026-02-07T00:30:00.000Z",
      "end_datetime": null,
      "venue": {
        "name": "Spectrum Center",
        "address": "333 East Trade Street",
        "neighborhood": "Uptown",
        "lat": 35.225222,
        "lng": -80.839921
      },
      "category": [
        "sports"
      ],
      "price": {
        "min": null,
        "max": null,
        "currency": "USD",
        "notes": "See website"
      },
      "image": "https://s1.ticketm.net/dam/a/380/bf11c4a6-7591-40d0-babc-f357525e0380_TABLET_LANDSCAPE_LARGE_16_9.jpg",
      "source": {
        "name": "Ticketmaster API",
        "url": "https://app.ticketmaster.com/discovery/v2/events",
        "scraped_at": "2026-02-02T15:42:01.511Z"
      },
      "url": "https://www.ticketmaster.com/wwe-friday-night-smackdown-charlotte-north-carolina-02-06-2026/event/2D006366F8139686",
      "confidence": 1,
      "tags": [
        "ticketmaster-api",
        "sports"
      ],
      "_rank_score": 65
    },
    {
      "id": "4d27cfa7cb1a213c6486834be985a0e095f08cf8",
      "title": "THE MOVEMENT - Visions Tour 2026 with Tropidelic",
      "description": "Age Policy: 18+ Valid ID required for entry into venue / Under 18 permitted with parent (Accepted forms of ID: State Issued ID or Driver's License, Military ID, Passport.)",
      "start_datetime": "2026-02-10T01:00:00.000Z",
      "end_datetime": null,
      "venue": {
        "name": "Neighborhood Theatre Main Room",
        "address": "511 E 36th St",
        "neighborhood": "",
        "lat": 35.247447,
        "lng": -80.803888
      },
      "category": [
        "concert",
        "nightlife"
      ],
      "price": {
        "min": null,
        "max": null,
        "currency": "USD",
        "notes": "See website"
      },
      "image": "https://s1.ticketm.net/dam/a/3bc/2e8e69b1-be78-4670-ae2b-a6d2f77903bc_RETINA_PORTRAIT_3_2.jpg",
      "source": {
        "name": "Ticketmaster API",
        "url": "https://app.ticketmaster.com/discovery/v2/events",
        "scraped_at": "2026-02-02T15:42:01.511Z"
      },
      "url": "https://www.ticketmaster.com/the-movement-visions-tour-2026-with-charlotte-north-carolina-02-09-2026/event/2D00633702AE99F1",
      "confidence": 1,
      "tags": [
        "ticketmaster-api",
        "music"
      ],
      "_rank_score": 65
    },
    {
      "id": "a283a98d5f2a7e98ff753b6e870859c4c3ca0e84",
      "title": "LOVE IS KING Tour - Evening with Gregory Porter",
      "description": "Doors 6:30pm. Show 7:30pm With his rich baritone voice and his mastery of the deepest traditions of soul, jazz and gospel, Gregory Porter has established himself as one of America's most versatile and acclaimed vocalists. His artistry and sensitivity is plain to the ear whether he's putting his stamp on beloved standards by heroes like Nat \"King\" Cole or demonstrating his own writing talents with original songs strong enough to stand with the many classics in his repertoire. Produced by Troy Miller (Jamie Cullum, Laura Mvula), All Rise is Porter's sixth studio album and fourth for the iconic Blue Note label. Like his 2013 breakthrough Liquid Spirit - the Grammy Award winner for Best Jazz Vocal Album - Porter's latest is a confident display of his many gifts, starting with his ability to convey feelings of both exaltation and sadness with uncommon directness and warmth.",
      "start_datetime": "2026-02-11T00:30:00.000Z",
      "end_datetime": null,
      "venue": {
        "name": "Ovens Auditorium",
        "address": "2900 E Independence Boulevard",
        "neighborhood": "East Charlotte",
        "lat": 35.2050931,
        "lng": -80.7953024
      },
      "category": [
        "concert",
        "nightlife"
      ],
      "price": {
        "min": null,
        "max": null,
        "currency": "USD",
        "notes": "See website"
      },
      "image": "https://s1.ticketm.net/dam/a/ba3/270590ab-2fd8-4ad8-b254-6400fb27aba3_1868271_RETINA_PORTRAIT_3_2.jpg",
      "source": {
        "name": "Ticketmaster API",
        "url": "https://app.ticketmaster.com/discovery/v2/events",
        "scraped_at": "2026-02-02T15:42:01.512Z"
      },
      "url": "https://www.ticketmaster.com/love-is-king-tour-evening-with-charlotte-north-carolina-02-10-2026/event/2D00636AF7F41730",
      "confidence": 1,
      "tags": [
        "ticketmaster-api",
        "music"
      ],
      "_rank_score": 65
    },
    {
      "id": "95a4f10b0b168409e9b06bc66851ca3cff22a5e5",
      "title": "Don't Be Cruel: The Elvis Experience",
      "description": "ACCESSIBILITY - Accessible seating is available online through Ticketmaster by filtering on the ADA Icon and selecting Accessible Seats. Note: the Carolina Theatre has the original, historic stairs in the balcony. Please take that into consideration when buying balcony tickets. CASHLESS VENUE - the Carolina Theatre services all credit and debit payments only. No cash accepted at the box office or bar. BAG POLICY - We encourage you to pack light with only the necessities to make the entry process as soon as possible. Bags are allowed and are subject to search upon entry. Exceptions will be made for necessary medical equipment or accommodations.",
      "start_datetime": "2026-02-11T00:30:00.000Z",
      "end_datetime": null,
      "venue": {
        "name": "The Carolina",
        "address": "Carolina Theatre Charlotte Belk Place - 230 North Tryon",
        "neighborhood": "",
        "lat": 35.22827319,
        "lng": -80.84086174
      },
      "category": [
        "concert",
        "nightlife"
      ],
      "price": {
        "min": null,
        "max": null,
        "currency": "USD",
        "notes": "See website"
      },
      "image": "https://s1.ticketm.net/dam/e/0b3/4f438b74-bb00-4826-afb1-46f614d4b0b3_TABLET_LANDSCAPE_LARGE_16_9.jpg",
      "source": {
        "name": "Ticketmaster API",
        "url": "https://app.ticketmaster.com/discovery/v2/events",
        "scraped_at": "2026-02-02T15:42:01.512Z"
      },
      "url": "https://www.ticketmaster.com/dont-be-cruel-the-elvis-experience-charlotte-north-carolina-02-10-2026/event/2D00635CCE37C6DA",
      "confidence": 1,
      "tags": [
        "ticketmaster-api",
        "music"
      ],
      "_rank_score": 65
    },
    {
      "id": "f053c237c1f7a51e7956bbe6eedf7b556378ec7f",
      "title": "Nine Inch Nails - Peel It Back Tour 2026",
      "description": "Nine Inch Nails - Peel It Back Tour 2026 at Spectrum Center",
      "start_datetime": "2026-02-11T01:00:00.000Z",
      "end_datetime": null,
      "venue": {
        "name": "Spectrum Center",
        "address": "333 East Trade Street",
        "neighborhood": "Uptown",
        "lat": 35.225222,
        "lng": -80.839921
      },
      "category": [
        "concert",
        "nightlife"
      ],
      "price": {
        "min": null,
        "max": null,
        "currency": "USD",
        "notes": "See website"
      },
      "image": "https://s1.ticketm.net/dam/a/8ec/fc59ad2d-314b-4cd2-b840-cfc8370248ec_TABLET_LANDSCAPE_16_9.jpg",
      "source": {
        "name": "Ticketmaster API",
        "url": "https://app.ticketmaster.com/discovery/v2/events",
        "scraped_at": "2026-02-02T15:42:01.512Z"
      },
      "url": "https://www.ticketmaster.com/nine-inch-nails-peel-it-back-charlotte-north-carolina-02-10-2026/event/2D00633DB8B85144",
      "confidence": 1,
      "tags": [
        "ticketmaster-api",
        "music"
      ],
      "_rank_score": 65
    },
    {
      "id": "16829f591f4048e75335def47b3d9bac0921ccd7",
      "title": "Jonah Kagen - Sunflowers & Leather Tour",
      "description": "Age Policy: 18+ Valid ID required for entry into venue / Under 18 permitted with parent (Accepted forms of ID: State Issued ID or Driver's License, Military ID, Passport.)",
      "start_datetime": "2026-02-11T01:00:00.000Z",
      "end_datetime": null,
      "venue": {
        "name": "Neighborhood Theatre Main Room",
        "address": "511 E 36th St",
        "neighborhood": "",
        "lat": 35.247447,
        "lng": -80.803888
      },
      "category": [
        "concert",
        "nightlife"
      ],
      "price": {
        "min": null,
        "max": null,
        "currency": "USD",
        "notes": "See website"
      },
      "image": "https://s1.ticketm.net/dam/e/cb6/f3b643f0-cd66-4ffa-8920-287c6f3b0cb6_TABLET_LANDSCAPE_16_9.jpg",
      "source": {
        "name": "Ticketmaster API",
        "url": "https://app.ticketmaster.com/discovery/v2/events",
        "scraped_at": "2026-02-02T15:42:01.512Z"
      },
      "url": "https://www.ticketmaster.com/jonah-kagen-sunflowers-leather-tour-charlotte-north-carolina-02-10-2026/event/2D006342B7469C44",
      "confidence": 1,
      "tags": [
        "ticketmaster-api",
        "music"
      ],
      "_rank_score": 65
    },
    {
      "id": "7228b9e9338366e6791d602ba2de7a892f64e0cf",
      "title": "Tyler Braden - Devila and a Prayer Tour",
      "description": "Tyler Braden - Devila and a Prayer Tour at Neighborhood Theater",
      "start_datetime": "2026-02-15T01:00:00.000Z",
      "end_datetime": null,
      "venue": {
        "name": "Neighborhood Theater",
        "address": "511 E 36th Street",
        "neighborhood": "",
        "lat": 35.24809,
        "lng": -80.80386
      },
      "category": [
        "concert",
        "nightlife"
      ],
      "price": {
        "min": null,
        "max": null,
        "currency": "USD",
        "notes": "See website"
      },
      "image": "https://s1.ticketm.net/dam/a/bcc/7006d121-67d1-4145-b6a7-072e00f82bcc_RETINA_PORTRAIT_3_2.jpg",
      "source": {
        "name": "Ticketmaster API",
        "url": "https://app.ticketmaster.com/discovery/v2/events",
        "scraped_at": "2026-02-02T15:42:01.512Z"
      },
      "url": "https://wl.eventim.us/event/TYLER-BRADEN-devil-and-a-prayer-TOUR/662064?afflky=MaxxMusic",
      "confidence": 1,
      "tags": [
        "ticketmaster-api",
        "music"
      ],
      "_rank_score": 65
    },
    {
      "id": "885ffd9af90ef49b039255b9828c39ce7ac82484",
      "title": "Lauren Spencer Smith: THE ART OF BEING A MESS TOUR",
      "description": "The Fillmore Is A General Admission Standing Room Only Venue Unless Otherwise Noted. All Ages Welcome Doors: 7:00PM Show: 8:00PM Ticket prices will increase the day of the show. All dates, acts, and ticket prices subject to change without notice. All tickets are subject to applicable service fees via all points of purchase. To further Lauren Spencer Smith's support of young people facing housing insecurity, hunger, and addiction, $1 per ticket will be paid from Live Nation to PLUS1 for the Lauren Spencer Smith Fund, supporting organizations providing critical care and support. www.plus1.org No portion of the ticket purchase is tax deductible.",
      "start_datetime": "2026-02-15T01:00:00.000Z",
      "end_datetime": null,
      "venue": {
        "name": "The Fillmore Charlotte",
        "address": "820 Hamilton Street",
        "neighborhood": "",
        "lat": 35.239095,
        "lng": -80.845519
      },
      "category": [
        "concert",
        "nightlife"
      ],
      "price": {
        "min": null,
        "max": null,
        "currency": "USD",
        "notes": "See website"
      },
      "image": "https://s1.ticketm.net/dam/a/1fd/6ec58e06-e186-4a20-bd31-444ff7c541fd_TABLET_LANDSCAPE_LARGE_16_9.jpg",
      "source": {
        "name": "Ticketmaster API",
        "url": "https://app.ticketmaster.com/discovery/v2/events",
        "scraped_at": "2026-02-02T15:42:01.512Z"
      },
      "url": "https://www.ticketmaster.com/lauren-spencer-smith-the-art-of-charlotte-north-carolina-02-14-2026/event/2D0062C292F217D5",
      "confidence": 1,
      "tags": [
        "ticketmaster-api",
        "music"
      ],
      "_rank_score": 65
    },
    {
      "id": "15ac6dd9984106e3a27bf0d2ebf8a539b567d926",
      "title": "Tyler Braden - Ages 18+",
      "description": "Tyler Braden - Ages 18+ at Neighborhood Theatre",
      "start_datetime": "2026-02-15T01:00:00.000Z",
      "end_datetime": null,
      "venue": {
        "name": "Neighborhood Theatre",
        "address": "511 East 36th St",
        "neighborhood": "",
        "lat": 35.219002,
        "lng": -80.787598
      },
      "category": [
        "concert",
        "nightlife"
      ],
      "price": {
        "min": null,
        "max": null,
        "currency": "USD",
        "notes": "See website"
      },
      "image": "https://s1.ticketm.net/dam/c/060/c5c08e7a-9912-456c-a060-2758be94e060_105881_TABLET_LANDSCAPE_3_2.jpg",
      "source": {
        "name": "Ticketmaster API",
        "url": "https://app.ticketmaster.com/discovery/v2/events",
        "scraped_at": "2026-02-02T15:42:01.512Z"
      },
      "url": "https://www.ticketmaster.com/event/Z7r9jZ1A7qOoM",
      "confidence": 1,
      "tags": [
        "ticketmaster-api",
        "music"
      ],
      "_rank_score": 65
    },
    {
      "id": "8525884fbfdfd334bc68ba319a7c0892a01ecaba",
      "title": "Boogie T (18 and Over)",
      "description": "Boogie T (18 and Over) at Blackbox Theater - Charlotte",
      "start_datetime": "2026-02-15T03:00:00.000Z",
      "end_datetime": null,
      "venue": {
        "name": "Blackbox Theater - Charlotte",
        "address": "421 East Sugar Creek Rd",
        "neighborhood": "",
        "lat": 35.2897,
        "lng": -80.730202
      },
      "category": [
        "concert",
        "nightlife"
      ],
      "price": {
        "min": null,
        "max": null,
        "currency": "USD",
        "notes": "See website"
      },
      "image": "https://s1.ticketm.net/dam/a/811/b4c546f9-1cae-4421-8942-bee0d3a5e811_1854821_RETINA_PORTRAIT_16_9.jpg",
      "source": {
        "name": "Ticketmaster API",
        "url": "https://app.ticketmaster.com/discovery/v2/events",
        "scraped_at": "2026-02-02T15:42:01.512Z"
      },
      "url": "https://www.ticketmaster.com/event/Z7r9jZ1A7qfeb",
      "confidence": 1,
      "tags": [
        "ticketmaster-api",
        "music"
      ],
      "_rank_score": 65
    },
    {
      "id": "00f50e1bf5e654bb57bcb9c8a92268037a127f1c",
      "title": "K-Pop Demon Ravers",
      "description": "The Underground Is A General Admission Standing Room Only Venue Unless Otherwise Noted. All Ages Welcome Doors: 11:00am Show: 12:00pm Ticket prices will increase the day of the show. All dates, acts, and ticket prices subject to change without notice. All tickets are subject to applicable service fees via all points of purchase.",
      "start_datetime": "2026-02-15T17:00:00.000Z",
      "end_datetime": null,
      "venue": {
        "name": "The Underground",
        "address": "820 Hamilton St",
        "neighborhood": "",
        "lat": 35.240299,
        "lng": -80.845314
      },
      "category": [
        "concert",
        "nightlife"
      ],
      "price": {
        "min": null,
        "max": null,
        "currency": "USD",
        "notes": "See website"
      },
      "image": "https://s1.ticketm.net/dam/e/91f/71da000e-5ac7-4ea9-88ee-78984201f91f_TABLET_LANDSCAPE_3_2.jpg",
      "source": {
        "name": "Ticketmaster API",
        "url": "https://app.ticketmaster.com/discovery/v2/events",
        "scraped_at": "2026-02-02T15:42:01.512Z"
      },
      "url": "https://www.ticketmaster.com/kpop-demon-ravers-charlotte-north-carolina-02-15-2026/event/2D00642F9B2CBE06",
      "confidence": 1,
      "tags": [
        "ticketmaster-api",
        "music"
      ],
      "_rank_score": 65
    },
    {
      "id": "ad526fd0542cac6d819cd852e75f80e9583a9707",
      "title": "Club 90s Presents Heated RivalRave (18+ ONLY)",
      "description": "The Fillmore Is A General Admission Standing Room Only Venue Unless Otherwise Noted. 18+ ONLY Doors: 9:00PM Show: 9:00PM Ticket prices will increase the day of the show. All dates, acts, and ticket prices subject to change without notice. All tickets are subject to applicable service fees via all points of purchase.",
      "start_datetime": "2026-02-16T02:00:00.000Z",
      "end_datetime": null,
      "venue": {
        "name": "The Fillmore Charlotte",
        "address": "820 Hamilton Street",
        "neighborhood": "",
        "lat": 35.239095,
        "lng": -80.845519
      },
      "category": [
        "concert",
        "nightlife"
      ],
      "price": {
        "min": null,
        "max": null,
        "currency": "USD",
        "notes": "See website"
      },
      "image": "https://s1.ticketm.net/dam/a/08f/dfb74e4a-95f6-46fd-bdb0-c699706e708f_1011401_TABLET_LANDSCAPE_LARGE_16_9.jpg",
      "source": {
        "name": "Ticketmaster API",
        "url": "https://app.ticketmaster.com/discovery/v2/events",
        "scraped_at": "2026-02-02T15:42:01.512Z"
      },
      "url": "https://www.ticketmaster.com/club-90s-presents-heated-rivalrave-18-charlotte-north-carolina-02-15-2026/event/2D00642D92165599",
      "confidence": 1,
      "tags": [
        "ticketmaster-api",
        "music"
      ],
      "_rank_score": 65
    },
    {
      "id": "bd40ffdcc17592eab8e3da28bbb8324d1eacc811",
      "title": "Charlotte Hornets vs. New Orleans Pelicans",
      "description": "Charlotte Hornets vs. New Orleans Pelicans at Spectrum Center",
      "start_datetime": "2026-02-02T20:00:00.000Z",
      "end_datetime": null,
      "venue": {
        "name": "Spectrum Center",
        "address": "333 East Trade Street",
        "neighborhood": "Uptown",
        "lat": 35.225222,
        "lng": -80.839921
      },
      "category": [
        "sports",
        "hornets"
      ],
      "price": {
        "min": null,
        "max": null,
        "currency": "USD",
        "notes": "See website"
      },
      "image": "https://s1.ticketm.net/dam/a/f48/2869041d-ebac-48fb-bf4f-54e797fa4f48_RETINA_PORTRAIT_3_2.jpg",
      "source": {
        "name": "Ticketmaster API",
        "url": "https://app.ticketmaster.com/discovery/v2/events",
        "scraped_at": "2026-02-02T15:42:01.511Z"
      },
      "url": "https://www.ticketmaster.com/charlotte-hornets-vs-new-orleans-pelicans-charlotte-north-carolina-02-02-2026/event/2D0062F9B4E698AA",
      "confidence": 1,
      "tags": [
        "ticketmaster-api",
        "sports"
      ],
      "_rank_score": 60
    },
    {
      "id": "861686a96431c05fb6b97a4f4f6a6984ce94fb57",
      "title": "Craig Ferguson",
      "description": "Craig Ferguson at Comedy Zone - Charlotte",
      "start_datetime": "2026-02-07T00:00:00.000Z",
      "end_datetime": null,
      "venue": {
        "name": "Comedy Zone - Charlotte",
        "address": "900 NC Music Factory Blvd B3",
        "neighborhood": "",
        "lat": 35.256302,
        "lng": -80.821198
      },
      "category": [
        "entertainment"
      ],
      "price": {
        "min": null,
        "max": null,
        "currency": "USD",
        "notes": "See website"
      },
      "image": "https://s1.ticketm.net/dam/a/6cf/4103d083-9c79-4b3b-8df0-2c23029a56cf_TABLET_LANDSCAPE_16_9.jpg",
      "source": {
        "name": "Ticketmaster API",
        "url": "https://app.ticketmaster.com/discovery/v2/events",
        "scraped_at": "2026-02-02T15:42:01.511Z"
      },
      "url": "https://www.ticketmaster.com/event/Z7r9jZ1A7qSA9",
      "confidence": 1,
      "tags": [
        "ticketmaster-api",
        "arts & theatre"
      ],
      "_rank_score": 60
    },
    {
      "id": "48d60d65c4c69eb5fde44230db7c54229a1baa61",
      "title": "Margaret Cho: Choligarchy",
      "description": "All Ages Welcome *MATURE CONTENT WARNING* Doors: 6:30PM Show: 7:30PM Ticket prices will increase the day of the show. All dates, acts, and ticket prices subject to change without notice. All tickets are subject to applicable service fees via all points of purchase.",
      "start_datetime": "2026-02-07T00:30:00.000Z",
      "end_datetime": null,
      "venue": {
        "name": "The Fillmore Charlotte",
        "address": "820 Hamilton Street",
        "neighborhood": "",
        "lat": 35.239095,
        "lng": -80.845519
      },
      "category": [
        "entertainment"
      ],
      "price": {
        "min": null,
        "max": null,
        "currency": "USD",
        "notes": "See website"
      },
      "image": "https://s1.ticketm.net/dam/a/881/853bc405-3922-4368-bed0-127532b30881_RETINA_PORTRAIT_3_2.jpg",
      "source": {
        "name": "Ticketmaster API",
        "url": "https://app.ticketmaster.com/discovery/v2/events",
        "scraped_at": "2026-02-02T15:42:01.511Z"
      },
      "url": "https://www.ticketmaster.com/margaret-cho-choligarchy-charlotte-north-carolina-02-06-2026/event/2D0062E8B0D72D12",
      "confidence": 1,
      "tags": [
        "ticketmaster-api",
        "arts & theatre"
      ],
      "_rank_score": 60
    },
    {
      "id": "d97c76b6a5134c9986739bd19e7e843899f37d76",
      "title": "Stardew Valley: Symphony Of Seasons",
      "description": "Doors 7pm. Show 8pm.",
      "start_datetime": "2026-02-07T01:00:00.000Z",
      "end_datetime": null,
      "venue": {
        "name": "Ovens Auditorium",
        "address": "2900 E Independence Boulevard",
        "neighborhood": "East Charlotte",
        "lat": 35.2050931,
        "lng": -80.7953024
      },
      "category": [
        "entertainment"
      ],
      "price": {
        "min": null,
        "max": null,
        "currency": "USD",
        "notes": "See website"
      },
      "image": "https://s1.ticketm.net/dam/a/362/aa47d872-7fbb-4c23-b869-59029f242362_RETINA_PORTRAIT_3_2.jpg",
      "source": {
        "name": "Ticketmaster API",
        "url": "https://app.ticketmaster.com/discovery/v2/events",
        "scraped_at": "2026-02-02T15:42:01.511Z"
      },
      "url": "https://www.ticketmaster.com/stardew-valley-symphony-of-seasons-charlotte-north-carolina-02-06-2026/event/2D00628FAC384334",
      "confidence": 1,
      "tags": [
        "ticketmaster-api",
        "arts & theatre"
      ],
      "_rank_score": 60
    },
    {
      "id": "25c31af4f5574a9c76a01a2f8f62dd41873ce448",
      "title": "Shaft",
      "description": "The mob wants Harlem back. But they're gonna get Shaft. Richard Roundtree stars as New York City private detective John Shaft. He's cool, tough, and won't back down to anybody. But when the New York Mafia wants to take over the Harlem drug trade, they kidnap local crime lord Bumpy Jonas' (Moses Gunn) daughter. Now, in the middle of a war between mobsters that's ready to ignite a racial tinderbox, Jonas hires the one man tough enough to get his daughter back?John Shaft",
      "start_datetime": "2026-02-07T00:00:00.000Z",
      "end_datetime": null,
      "venue": {
        "name": "The Carolina",
        "address": "Carolina Theatre Charlotte Belk Place - 230 North Tryon",
        "neighborhood": "",
        "lat": 35.22827319,
        "lng": -80.84086174
      },
      "category": [
        "special"
      ],
      "price": {
        "min": null,
        "max": null,
        "currency": "USD",
        "notes": "See website"
      },
      "image": "https://s1.ticketm.net/dam/e/2f6/74c4ebd8-0555-4d1d-ade0-b736837bb2f6_TABLET_LANDSCAPE_16_9.jpg",
      "source": {
        "name": "Ticketmaster API",
        "url": "https://app.ticketmaster.com/discovery/v2/events",
        "scraped_at": "2026-02-02T15:42:01.511Z"
      },
      "url": "https://www.ticketmaster.com/shaft-charlotte-north-carolina-02-06-2026/event/2D006427E37CCDC6",
      "confidence": 1,
      "tags": [
        "ticketmaster-api",
        "film"
      ],
      "_rank_score": 55
    },
    {
      "id": "e349114c33d00bb7969bbb5758a5ba16fa7aaf6d",
      "title": "Charlotte Checkers vs. Hartford Wolf Pack",
      "description": "BAG POLICY: Any non-clear bag larger than 4.5\" x 6.5\" is not permitted.",
      "start_datetime": "2026-02-14T21:00:00.000Z",
      "end_datetime": null,
      "venue": {
        "name": "Bojangles Coliseum",
        "address": "2700 E Independence Boulevard",
        "neighborhood": "East Charlotte",
        "lat": 35.2050931,
        "lng": -80.7953024
      },
      "category": [
        "sports"
      ],
      "price": {
        "min": null,
        "max": null,
        "currency": "USD",
        "notes": "See website"
      },
      "image": "https://s1.ticketm.net/dam/a/8d9/818ee4bb-df3e-4d58-8468-c23e293418d9_851601_RETINA_PORTRAIT_16_9.jpg",
      "source": {
        "name": "Ticketmaster API",
        "url": "https://app.ticketmaster.com/discovery/v2/events",
        "scraped_at": "2026-02-02T15:42:01.512Z"
      },
      "url": "https://www.ticketmaster.com/charlotte-checkers-vs-hartford-wolf-pack-charlotte-north-carolina-02-14-2026/event/2D00631AE662627E",
      "confidence": 1,
      "tags": [
        "ticketmaster-api",
        "sports"
      ],
      "_rank_score": 55
    },
    {
      "id": "4b0e691859ec43cdb1508c2118c4ecf3c542ad49",
      "title": "WWE SmackDown Luxury",
      "description": "WWE SmackDown Luxury at Spectrum Center",
      "start_datetime": "2026-02-07T00:30:00.000Z",
      "end_datetime": null,
      "venue": {
        "name": "Spectrum Center",
        "address": "333 E Trade St",
        "neighborhood": "Uptown",
        "lat": 35.225061,
        "lng": -80.839334
      },
      "category": [
        "special"
      ],
      "price": {
        "min": null,
        "max": null,
        "currency": "USD",
        "notes": "See website"
      },
      "image": "https://s1.ticketm.net/dam/c/8cf/a6653880-7899-4f67-8067-1f95f4d158cf_124761_TABLET_LANDSCAPE_16_9.jpg",
      "source": {
        "name": "Ticketmaster API",
        "url": "https://app.ticketmaster.com/discovery/v2/events",
        "scraped_at": "2026-02-02T15:42:01.511Z"
      },
      "url": "",
      "confidence": 0.9,
      "tags": [
        "ticketmaster-api"
      ],
      "_rank_score": 52
    },
    {
      "id": "5eea5b274dc2fe16a073ad4917c0448a705676c4",
      "title": "Twinsick (18 and Over)",
      "description": "Twinsick (18 and Over) at Blackbox Theater - Charlotte",
      "start_datetime": "2026-02-03T03:00:00.000Z",
      "end_datetime": null,
      "venue": {
        "name": "Blackbox Theater - Charlotte",
        "address": "421 East Sugar Creek Rd",
        "neighborhood": "",
        "lat": 35.2897,
        "lng": -80.730202
      },
      "category": [
        "special"
      ],
      "price": {
        "min": null,
        "max": null,
        "currency": "USD",
        "notes": "See website"
      },
      "image": "https://s1.ticketm.net/dam/c/f51/ee785ed6-f806-4195-98f4-69f67e09df51_106201_TABLET_LANDSCAPE_16_9.jpg",
      "source": {
        "name": "Ticketmaster API",
        "url": "https://app.ticketmaster.com/discovery/v2/events",
        "scraped_at": "2026-02-02T15:42:01.511Z"
      },
      "url": "https://www.ticketmaster.com/event/Z7r9jZ1A7ObA0",
      "confidence": 1,
      "tags": [
        "ticketmaster-api",
        "undefined"
      ],
      "_rank_score": 50
    },
    {
      "id": "ac07a3ea8a1e83816cb1c7bd741bade72cb263f6",
      "title": "Kamala Harris - Book Add-On",
      "description": "Add a copy of Kamala Harris's book 107 DAYS to your show experience. An event ticket must be purchased separately.",
      "start_datetime": "2026-02-05T00:00:00.000Z",
      "end_datetime": null,
      "venue": {
        "name": "Ovens Auditorium",
        "address": "2900 E Independence Boulevard",
        "neighborhood": "East Charlotte",
        "lat": 35.2050931,
        "lng": -80.7953024
      },
      "category": [
        "special"
      ],
      "price": {
        "min": null,
        "max": null,
        "currency": "USD",
        "notes": "See website"
      },
      "image": "https://s1.ticketm.net/dam/c/03e/e15ef00f-2c87-4421-ae61-d740851a703e_105891_TABLET_LANDSCAPE_LARGE_16_9.jpg",
      "source": {
        "name": "Ticketmaster API",
        "url": "https://app.ticketmaster.com/discovery/v2/events",
        "scraped_at": "2026-02-02T15:42:01.511Z"
      },
      "url": "https://www.ticketmaster.com/kamala-harris-book-addon-charlotte-north-carolina-02-04-2026/event/2D006384C187DE3E",
      "confidence": 1,
      "tags": [
        "ticketmaster-api",
        "miscellaneous"
      ],
      "_rank_score": 50
    },
    {
      "id": "83fced3f8d44e8098621414820e9662cc914288b",
      "title": "A Conversation with Kamala Harris",
      "description": "Doors 6pm. Show 7pm.",
      "start_datetime": "2026-02-05T00:00:00.000Z",
      "end_datetime": null,
      "venue": {
        "name": "Ovens Auditorium",
        "address": "2900 E Independence Boulevard",
        "neighborhood": "East Charlotte",
        "lat": 35.2050931,
        "lng": -80.7953024
      },
      "category": [
        "special"
      ],
      "price": {
        "min": null,
        "max": null,
        "currency": "USD",
        "notes": "See website"
      },
      "image": "https://s1.ticketm.net/dam/a/12a/918409e0-2cb9-4324-9802-257e63b9d12a_RETINA_LANDSCAPE_16_9.jpg",
      "source": {
        "name": "Ticketmaster API",
        "url": "https://app.ticketmaster.com/discovery/v2/events",
        "scraped_at": "2026-02-02T15:42:01.511Z"
      },
      "url": "https://www.ticketmaster.com/a-conversation-with-kamala-harris-charlotte-north-carolina-02-04-2026/event/2D006384C184DE3C",
      "confidence": 1,
      "tags": [
        "ticketmaster-api",
        "miscellaneous"
      ],
      "_rank_score": 50
    },
    {
      "id": "11275f6a4e773f3a62880bc0055390d2d8a4300e",
      "title": "Urban Trivia Live - 21+ ONLY",
      "description": "21+ ONLY Doors: 7:00PM Show: 8:00PM Ticket prices will increase the day of the show. All dates, acts, and ticket prices subject to change without notice. All tickets are subject to applicable service fees via all points of purchase.",
      "start_datetime": "2026-02-08T01:00:00.000Z",
      "end_datetime": null,
      "venue": {
        "name": "The Fillmore Charlotte",
        "address": "820 Hamilton Street",
        "neighborhood": "",
        "lat": 35.239095,
        "lng": -80.845519
      },
      "category": [
        "entertainment"
      ],
      "price": {
        "min": null,
        "max": null,
        "currency": "USD",
        "notes": "See website"
      },
      "image": "https://s1.ticketm.net/dam/c/393/b74d3ddc-a5f3-4e09-a801-89c36b774393_106071_RETINA_PORTRAIT_16_9.jpg",
      "source": {
        "name": "Ticketmaster API",
        "url": "https://app.ticketmaster.com/discovery/v2/events",
        "scraped_at": "2026-02-02T15:42:01.511Z"
      },
      "url": "https://www.ticketmaster.com/urban-trivia-live-21-only-charlotte-north-carolina-02-07-2026/event/2D006357E336C6C8",
      "confidence": 1,
      "tags": [
        "ticketmaster-api",
        "arts & theatre"
      ],
      "_rank_score": 50
    },
    {
      "id": "ff352cda1dc7fe6472d473d7b05b69d5ac4fb067",
      "title": "Riverdance 30 - The New Generation",
      "description": "BAG POLICY: Any non-clear bag larger than 4.5\" x 6.5\" is not permitted.All purchase transactions will be cashless. Purchases can be made with a debit card or credit card; matching ID required.All dates, acts, & ticket prices subject to change without notice.All tickets are subject to applicable service fees via all points of sale.",
      "start_datetime": "2026-02-14T00:30:00.000Z",
      "end_datetime": null,
      "venue": {
        "name": "Ovens Auditorium",
        "address": "2900 E Independence Boulevard",
        "neighborhood": "East Charlotte",
        "lat": 35.2050931,
        "lng": -80.7953024
      },
      "category": [
        "entertainment"
      ],
      "price": {
        "min": null,
        "max": null,
        "currency": "USD",
        "notes": "See website"
      },
      "image": "https://s1.ticketm.net/dam/a/038/62cb1def-603e-4722-a458-1858c9bb6038_RETINA_PORTRAIT_3_2.jpg",
      "source": {
        "name": "Ticketmaster API",
        "url": "https://app.ticketmaster.com/discovery/v2/events",
        "scraped_at": "2026-02-02T15:42:01.512Z"
      },
      "url": "https://www.ticketmaster.com/riverdance-30-the-new-generation-charlotte-north-carolina-02-13-2026/event/2D00638FC552CE9C",
      "confidence": 1,
      "tags": [
        "ticketmaster-api",
        "arts & theatre"
      ],
      "_rank_score": 50
    },
    {
      "id": "4538fe5500dbb38609e1eb7f4926a0e85c3b7979",
      "title": "Postgame Pass - Section 107",
      "description": "Postgame Pass - Section 107 at Spectrum Center",
      "start_datetime": "2026-02-03T00:00:00.000Z",
      "end_datetime": null,
      "venue": {
        "name": "Spectrum Center",
        "address": "333 East Trade",
        "neighborhood": "Uptown",
        "lat": 35.22506060000002,
        "lng": -80.8393335
      },
      "category": [
        "special"
      ],
      "price": {
        "min": null,
        "max": null,
        "currency": "USD",
        "notes": "See website"
      },
      "image": "https://s1.ticketm.net/dam/c/8cf/a6653880-7899-4f67-8067-1f95f4d158cf_124761_TABLET_LANDSCAPE_16_9.jpg",
      "source": {
        "name": "Ticketmaster API",
        "url": "https://app.ticketmaster.com/discovery/v2/events",
        "scraped_at": "2026-02-02T15:42:01.511Z"
      },
      "url": "",
      "confidence": 0.9,
      "tags": [
        "ticketmaster-api"
      ],
      "_rank_score": 47
    },
    {
      "id": "555aa1d2624f8a737b8360837fe5be3f1e3ef553",
      "title": "Postgame Pass - Section 103",
      "description": "Postgame Pass - Section 103 at Spectrum Center",
      "start_datetime": "2026-02-03T00:00:00.000Z",
      "end_datetime": null,
      "venue": {
        "name": "Spectrum Center",
        "address": "333 East Trade",
        "neighborhood": "Uptown",
        "lat": 35.22506060000002,
        "lng": -80.8393335
      },
      "category": [
        "special"
      ],
      "price": {
        "min": null,
        "max": null,
        "currency": "USD",
        "notes": "See website"
      },
      "image": "https://s1.ticketm.net/dam/c/8cf/a6653880-7899-4f67-8067-1f95f4d158cf_124761_TABLET_LANDSCAPE_16_9.jpg",
      "source": {
        "name": "Ticketmaster API",
        "url": "https://app.ticketmaster.com/discovery/v2/events",
        "scraped_at": "2026-02-02T15:42:01.511Z"
      },
      "url": "",
      "confidence": 0.9,
      "tags": [
        "ticketmaster-api"
      ],
      "_rank_score": 47
    },
    {
      "id": "f7fc199c48fcd36d0ac997f154d7d4465c7832b8",
      "title": "Suite Access Pass - Hornets vs. Pelicans",
      "description": "Suite Access Pass - Hornets vs. Pelicans at Spectrum Center",
      "start_datetime": "2026-02-03T00:00:00.000Z",
      "end_datetime": null,
      "venue": {
        "name": "Spectrum Center",
        "address": "333 E Trade St",
        "neighborhood": "Uptown",
        "lat": 35.225061,
        "lng": -80.839334
      },
      "category": [
        "special"
      ],
      "price": {
        "min": null,
        "max": null,
        "currency": "USD",
        "notes": "See website"
      },
      "image": "https://s1.ticketm.net/dam/c/8cf/a6653880-7899-4f67-8067-1f95f4d158cf_124761_TABLET_LANDSCAPE_16_9.jpg",
      "source": {
        "name": "Ticketmaster API",
        "url": "https://app.ticketmaster.com/discovery/v2/events",
        "scraped_at": "2026-02-02T15:42:01.511Z"
      },
      "url": "",
      "confidence": 0.9,
      "tags": [
        "ticketmaster-api"
      ],
      "_rank_score": 47
    },
    {
      "id": "e58d276bfe8d6fabb6e975ea8e34721eb4f6ba3e",
      "title": "Ricardo Arjona Luxury",
      "description": "Ricardo Arjona Luxury at Spectrum Center",
      "start_datetime": "2026-02-04T01:00:00.000Z",
      "end_datetime": null,
      "venue": {
        "name": "Spectrum Center",
        "address": "333 E Trade St",
        "neighborhood": "Uptown",
        "lat": 35.225061,
        "lng": -80.839334
      },
      "category": [
        "special"
      ],
      "price": {
        "min": null,
        "max": null,
        "currency": "USD",
        "notes": "See website"
      },
      "image": "https://s1.ticketm.net/dam/c/8cf/a6653880-7899-4f67-8067-1f95f4d158cf_124761_TABLET_LANDSCAPE_16_9.jpg",
      "source": {
        "name": "Ticketmaster API",
        "url": "https://app.ticketmaster.com/discovery/v2/events",
        "scraped_at": "2026-02-02T15:42:01.511Z"
      },
      "url": "",
      "confidence": 0.9,
      "tags": [
        "ticketmaster-api"
      ],
      "_rank_score": 47
    },
    {
      "id": "3c485ce96b789b429eb216eed06cf11c6b20617b",
      "title": "Do The Right Thing",
      "description": "Racial tensions grow in a Brooklyn neighborhood on the hottest day of the summer while everyone tries to cope with the heat. Spike Lee received an Oscar nomination for his screenplay.",
      "start_datetime": "2026-02-08T00:00:00.000Z",
      "end_datetime": null,
      "venue": {
        "name": "The Carolina",
        "address": "Carolina Theatre Charlotte Belk Place - 230 North Tryon",
        "neighborhood": "",
        "lat": 35.22827319,
        "lng": -80.84086174
      },
      "category": [
        "special"
      ],
      "price": {
        "min": null,
        "max": null,
        "currency": "USD",
        "notes": "See website"
      },
      "image": "https://s1.ticketm.net/dam/e/d88/f1c675f6-e79c-4e8a-926a-d02ace1a2d88_TABLET_LANDSCAPE_16_9.jpg",
      "source": {
        "name": "Ticketmaster API",
        "url": "https://app.ticketmaster.com/discovery/v2/events",
        "scraped_at": "2026-02-02T15:42:01.511Z"
      },
      "url": "https://www.ticketmaster.com/do-the-right-thing-charlotte-north-carolina-02-07-2026/event/2D006427E37FCDC9",
      "confidence": 1,
      "tags": [
        "ticketmaster-api",
        "film"
      ],
      "_rank_score": 45
    },
    {
      "id": "57559478019f7674fc8314977c4d721d2447cbe9",
      "title": "Charlotte Hornets vs. Detroit Pistons",
      "description": "Charlotte Hornets vs. Detroit Pistons at Spectrum Center",
      "start_datetime": "2026-02-10T00:00:00.000Z",
      "end_datetime": null,
      "venue": {
        "name": "Spectrum Center",
        "address": "333 East Trade Street",
        "neighborhood": "Uptown",
        "lat": 35.225222,
        "lng": -80.839921
      },
      "category": [
        "sports",
        "hornets"
      ],
      "price": {
        "min": null,
        "max": null,
        "currency": "USD",
        "notes": "See website"
      },
      "image": "https://s1.ticketm.net/dam/a/f48/2869041d-ebac-48fb-bf4f-54e797fa4f48_RETINA_PORTRAIT_3_2.jpg",
      "source": {
        "name": "Ticketmaster API",
        "url": "https://app.ticketmaster.com/discovery/v2/events",
        "scraped_at": "2026-02-02T15:42:01.511Z"
      },
      "url": "https://www.ticketmaster.com/charlotte-hornets-vs-detroit-pistons-charlotte-north-carolina-02-09-2026/event/2D0062F9B4E998AC",
      "confidence": 1,
      "tags": [
        "ticketmaster-api",
        "sports"
      ],
      "_rank_score": 45
    },
    {
      "id": "304ed0a2680cb4190ae40252cd0029de17ba61ba",
      "title": "Charlotte Hornets vs. Atlanta Hawks",
      "description": "Charlotte Hornets vs. Atlanta Hawks at Spectrum Center",
      "start_datetime": "2026-02-12T00:00:00.000Z",
      "end_datetime": null,
      "venue": {
        "name": "Spectrum Center",
        "address": "333 East Trade Street",
        "neighborhood": "Uptown",
        "lat": 35.225222,
        "lng": -80.839921
      },
      "category": [
        "sports",
        "hornets"
      ],
      "price": {
        "min": null,
        "max": null,
        "currency": "USD",
        "notes": "See website"
      },
      "image": "https://s1.ticketm.net/dam/a/f48/2869041d-ebac-48fb-bf4f-54e797fa4f48_RETINA_PORTRAIT_3_2.jpg",
      "source": {
        "name": "Ticketmaster API",
        "url": "https://app.ticketmaster.com/discovery/v2/events",
        "scraped_at": "2026-02-02T15:42:01.512Z"
      },
      "url": "https://www.ticketmaster.com/charlotte-hornets-vs-atlanta-hawks-charlotte-north-carolina-02-11-2026/event/2D0062F9B4EB98AE",
      "confidence": 1,
      "tags": [
        "ticketmaster-api",
        "sports"
      ],
      "_rank_score": 45
    },
    {
      "id": "ca30a922e8ee20801a10828dc5a87a763290eb5b",
      "title": "Dreamgirls",
      "description": "Adaptation of the Broadway hit about the ups and downs of a 1960s girl group. Jennifer Hudson won a Best Supporting Actress Oscar for her role.",
      "start_datetime": "2026-02-14T00:00:00.000Z",
      "end_datetime": null,
      "venue": {
        "name": "The Carolina",
        "address": "Carolina Theatre Charlotte Belk Place - 230 North Tryon",
        "neighborhood": "",
        "lat": 35.22827319,
        "lng": -80.84086174
      },
      "category": [
        "special"
      ],
      "price": {
        "min": null,
        "max": null,
        "currency": "USD",
        "notes": "See website"
      },
      "image": "https://s1.ticketm.net/dam/e/09e/138808c7-c4c4-45ec-9b66-11ff8cf4209e_RETINA_PORTRAIT_3_2.jpg",
      "source": {
        "name": "Ticketmaster API",
        "url": "https://app.ticketmaster.com/discovery/v2/events",
        "scraped_at": "2026-02-02T15:42:01.512Z"
      },
      "url": "https://www.ticketmaster.com/dreamgirls-charlotte-north-carolina-02-13-2026/event/2D006427E381CDCC",
      "confidence": 1,
      "tags": [
        "ticketmaster-api",
        "film"
      ],
      "_rank_score": 45
    },
    {
      "id": "d813c56de4fbf0643ec25a68dfac7b058cb7a1a8",
      "title": "The 9am Banger Presents: R&B at 9AM (21+)",
      "description": "The Underground Is A General Admission Standing Room Only Venue Unless Otherwise Noted. Ages 21+ Welcome Doors: 9:00AM Show:9:00AM Ticket prices will increase the day of the show. All dates, acts, and ticket prices subject to change without notice. All tickets are subject to applicable service fees via all points of purchase.",
      "start_datetime": "2026-02-14T14:00:00.000Z",
      "end_datetime": null,
      "venue": {
        "name": "The Underground",
        "address": "820 Hamilton St",
        "neighborhood": "",
        "lat": 35.240299,
        "lng": -80.845314
      },
      "category": [
        "special"
      ],
      "price": {
        "min": null,
        "max": null,
        "currency": "USD",
        "notes": "See website"
      },
      "image": "https://s1.ticketm.net/dam/a/a2c/b5d95e83-6127-4e32-ac53-1c2c98486a2c_TABLET_LANDSCAPE_3_2.jpg",
      "source": {
        "name": "Ticketmaster API",
        "url": "https://app.ticketmaster.com/discovery/v2/events",
        "scraped_at": "2026-02-02T15:42:01.512Z"
      },
      "url": "https://www.ticketmaster.com/the-9am-banger-presents-rb-at-charlotte-north-carolina-02-14-2026/event/2D00642FCDCB5450",
      "confidence": 1,
      "tags": [
        "ticketmaster-api",
        "miscellaneous"
      ],
      "_rank_score": 45
    },
    {
      "id": "373b5e343ef92a57b50ac2c011540ccb5eaee737",
      "title": "Charlotte Checkers vs. Hartford Wolf Pack",
      "description": "BAG POLICY: Any non-clear bag larger than 4.5\" x 6.5\" is not permitted.",
      "start_datetime": "2026-02-15T21:00:00.000Z",
      "end_datetime": null,
      "venue": {
        "name": "Bojangles Coliseum",
        "address": "2700 E Independence Boulevard",
        "neighborhood": "East Charlotte",
        "lat": 35.2050931,
        "lng": -80.7953024
      },
      "category": [
        "sports"
      ],
      "price": {
        "min": null,
        "max": null,
        "currency": "USD",
        "notes": "See website"
      },
      "image": "https://s1.ticketm.net/dam/a/8d9/818ee4bb-df3e-4d58-8468-c23e293418d9_851601_RETINA_PORTRAIT_16_9.jpg",
      "source": {
        "name": "Ticketmaster API",
        "url": "https://app.ticketmaster.com/discovery/v2/events",
        "scraped_at": "2026-02-02T15:42:01.512Z"
      },
      "url": "https://www.ticketmaster.com/charlotte-checkers-vs-hartford-wolf-pack-charlotte-north-carolina-02-15-2026/event/2D00631AE6656288",
      "confidence": 1,
      "tags": [
        "ticketmaster-api",
        "sports"
      ],
      "_rank_score": 45
    },
    {
      "id": "183ef0f60628faef4c1073d53d6c4192ffb28170",
      "title": "The Queens Luxury",
      "description": "The Queens Luxury at Spectrum Center",
      "start_datetime": "2026-02-14T01:00:00.000Z",
      "end_datetime": null,
      "venue": {
        "name": "Spectrum Center",
        "address": "333 E Trade St",
        "neighborhood": "Uptown",
        "lat": 35.225061,
        "lng": -80.839334
      },
      "category": [
        "special"
      ],
      "price": {
        "min": null,
        "max": null,
        "currency": "USD",
        "notes": "See website"
      },
      "image": "https://s1.ticketm.net/dam/c/8cf/a6653880-7899-4f67-8067-1f95f4d158cf_124761_TABLET_LANDSCAPE_16_9.jpg",
      "source": {
        "name": "Ticketmaster API",
        "url": "https://app.ticketmaster.com/discovery/v2/events",
        "scraped_at": "2026-02-02T15:42:01.512Z"
      },
      "url": "",
      "confidence": 0.9,
      "tags": [
        "ticketmaster-api"
      ],
      "_rank_score": 42
    },
    {
      "id": "3a5effe2c2fd6aa8f89f152c7396a43c5500fcee",
      "title": "Riverdance 30 - The New Generation",
      "description": "BAG POLICY: Any non-clear bag larger than 4.5\" x 6.5\" is not permitted.All purchase transactions will be cashless. Purchases can be made with a debit card or credit card; matching ID required.All dates, acts, & ticket prices subject to change without notice.All tickets are subject to applicable service fees via all points of sale.",
      "start_datetime": "2026-02-15T00:30:00.000Z",
      "end_datetime": null,
      "venue": {
        "name": "Ovens Auditorium",
        "address": "2900 E Independence Boulevard",
        "neighborhood": "East Charlotte",
        "lat": 35.2050931,
        "lng": -80.7953024
      },
      "category": [
        "entertainment"
      ],
      "price": {
        "min": null,
        "max": null,
        "currency": "USD",
        "notes": "See website"
      },
      "image": "https://s1.ticketm.net/dam/a/038/62cb1def-603e-4722-a458-1858c9bb6038_RETINA_PORTRAIT_3_2.jpg",
      "source": {
        "name": "Ticketmaster API",
        "url": "https://app.ticketmaster.com/discovery/v2/events",
        "scraped_at": "2026-02-02T15:42:01.512Z"
      },
      "url": "https://www.ticketmaster.com/riverdance-30-the-new-generation-charlotte-north-carolina-02-14-2026/event/2D00638FC557CE9E",
      "confidence": 1,
      "tags": [
        "ticketmaster-api",
        "arts & theatre"
      ],
      "_rank_score": 40
    },
    {
      "id": "8a4b553963959af67fd9338a13b86f68f6e9c21d",
      "title": "Sutton Foster",
      "description": "Sutton Foster at Knight Theater",
      "start_datetime": "2026-02-15T01:00:00.000Z",
      "end_datetime": null,
      "venue": {
        "name": "Knight Theater",
        "address": "430 South Tryon St",
        "neighborhood": "Uptown",
        "lat": 35.2242679,
        "lng": -80.8473758
      },
      "category": [
        "entertainment"
      ],
      "price": {
        "min": null,
        "max": null,
        "currency": "USD",
        "notes": "See website"
      },
      "image": "https://s1.ticketm.net/dam/a/184/6a7827b3-bff0-4ba8-b861-2e2844169184_TABLET_LANDSCAPE_16_9.jpg",
      "source": {
        "name": "Ticketmaster API",
        "url": "https://app.ticketmaster.com/discovery/v2/events",
        "scraped_at": "2026-02-02T15:42:01.512Z"
      },
      "url": "https://tix.blumenthalarts.org/online/default.asp?doWork::WScontent::loadArticle=Load&BOparam::WScontent::loadArticle::article_id=6B1DC86C-CE12-48C5-8F58-511452389137",
      "confidence": 1,
      "tags": [
        "ticketmaster-api",
        "arts & theatre"
      ],
      "_rank_score": 40
    },
    {
      "id": "9bc773eb88dfd83ebe0e1289b659f5e2ec470539",
      "title": "Courage & Democracy: Senator Doug Jones Live on Our New South podcast",
      "description": "Join us at the Carolina Theatre as the Levine Museum of the New South hosts a live recording of its award-winning podcast, Our New South, featuring Doug Jones, former U.S. Senator from Alabama. From the courtroom to the Capitol, Jones has spent his career standing up for justice and bridging divides. As the federal prosecutor who brought long-overdue accountability to the Ku Klux Klan members responsible for the 16th Street Baptist Church bombing and later as a senator representing Alabama, Jones has remained guided by integrity, empathy and a deep belief in doing what?s right. Hosted by journalist and Washington Post columnist Kevin Blackistone and historian Dr. Robert Greene II, Our New South sparks conversations about the people, places and ideas shaping the region today. In this special live episode, Jones will reflect on his journey and share what the New South means to him and the future he envisions for the region.",
      "start_datetime": "2026-02-12T00:00:00.000Z",
      "end_datetime": null,
      "venue": {
        "name": "The Carolina",
        "address": "Carolina Theatre Charlotte Belk Place - 230 North Tryon",
        "neighborhood": "",
        "lat": 35.22827319,
        "lng": -80.84086174
      },
      "category": [
        "special"
      ],
      "price": {
        "min": null,
        "max": null,
        "currency": "USD",
        "notes": "See website"
      },
      "image": "https://s1.ticketm.net/dam/e/700/89685ba4-abec-4cf0-a663-ed5998c2c700_TABLET_LANDSCAPE_3_2.jpg",
      "source": {
        "name": "Ticketmaster API",
        "url": "https://app.ticketmaster.com/discovery/v2/events",
        "scraped_at": "2026-02-02T15:42:01.512Z"
      },
      "url": "https://www.ticketmaster.com/courage-democracy-senator-doug-jones-live-charlotte-north-carolina-02-11-2026/event/2D006426E756C2DD",
      "confidence": 1,
      "tags": [
        "ticketmaster-api",
        "miscellaneous"
      ],
      "_rank_score": 35
    },
    {
      "id": "540597f6a03bd8f2a99b7c908d22e64aeae96cbf",
      "title": "Love And Basketball",
      "description": "This story tells of childhood adversaries and talented athletes who have a love for the game of basketball and each other. Each pursues their dream of basketball success through high school, college, and the pros, but along the way they must face their own personal hurdles.",
      "start_datetime": "2026-02-15T00:00:00.000Z",
      "end_datetime": null,
      "venue": {
        "name": "The Carolina",
        "address": "Carolina Theatre Charlotte Belk Place - 230 North Tryon",
        "neighborhood": "",
        "lat": 35.22827319,
        "lng": -80.84086174
      },
      "category": [
        "special"
      ],
      "price": {
        "min": null,
        "max": null,
        "currency": "USD",
        "notes": "See website"
      },
      "image": "https://s1.ticketm.net/dam/e/8ff/8eb81dd3-595a-4c10-a567-da15a8a938ff_TABLET_LANDSCAPE_3_2.jpg",
      "source": {
        "name": "Ticketmaster API",
        "url": "https://app.ticketmaster.com/discovery/v2/events",
        "scraped_at": "2026-02-02T15:42:01.512Z"
      },
      "url": "https://www.ticketmaster.com/love-and-basketball-charlotte-north-carolina-02-14-2026/event/2D006427E384CDD0",
      "confidence": 1,
      "tags": [
        "ticketmaster-api",
        "film"
      ],
      "_rank_score": 35
    },
    {
      "id": "43a231fcb0535ef53ef972ee0acc855dcb12e30c",
      "title": "Alex Sampson (Under 18 with parent or legal guardian)",
      "description": "Alex Sampson (Under 18 with parent or legal guardian) at The Evening Muse",
      "start_datetime": "2026-02-15T00:30:00.000Z",
      "end_datetime": null,
      "venue": {
        "name": "The Evening Muse",
        "address": "3227 N Davidson St,",
        "neighborhood": "",
        "lat": 35.219002,
        "lng": -80.787598
      },
      "category": [
        "special"
      ],
      "price": {
        "min": null,
        "max": null,
        "currency": "USD",
        "notes": "See website"
      },
      "image": "https://s1.ticketm.net/dam/c/f51/ee785ed6-f806-4195-98f4-69f67e09df51_106201_TABLET_LANDSCAPE_16_9.jpg",
      "source": {
        "name": "Ticketmaster API",
        "url": "https://app.ticketmaster.com/discovery/v2/events",
        "scraped_at": "2026-02-02T15:42:01.512Z"
      },
      "url": "https://www.ticketmaster.com/event/Z7r9jZ1A7qabM",
      "confidence": 1,
      "tags": [
        "ticketmaster-api",
        "undefined"
      ],
      "_rank_score": 35
    },
    {
      "id": "8d48e8c175f2e32ba9a4ac932a692014d2a8d784",
      "title": "The Princess and the Frog",
      "description": "A prince is transformed into a frog and accidentally curses a beautiful princess with an amphibian form as well when he kisses her in an attempt to break the spell. The two then go on a wild journey through the bayous of Louisiana in hopes of finding a voodoo priestess who may be able to restore their true forms.",
      "start_datetime": "2026-02-15T19:00:00.000Z",
      "end_datetime": null,
      "venue": {
        "name": "The Carolina",
        "address": "Carolina Theatre Charlotte Belk Place - 230 North Tryon",
        "neighborhood": "",
        "lat": 35.22827319,
        "lng": -80.84086174
      },
      "category": [
        "special"
      ],
      "price": {
        "min": null,
        "max": null,
        "currency": "USD",
        "notes": "See website"
      },
      "image": "https://s1.ticketm.net/dam/e/c3b/9573f900-41b3-4d66-a0eb-6a7532254c3b_SOURCE",
      "source": {
        "name": "Ticketmaster API",
        "url": "https://app.ticketmaster.com/discovery/v2/events",
        "scraped_at": "2026-02-02T15:42:01.512Z"
      },
      "url": "https://www.ticketmaster.com/the-princess-and-the-frog-charlotte-north-carolina-02-15-2026/event/2D006427E386CDD4",
      "confidence": 1,
      "tags": [
        "ticketmaster-api",
        "film"
      ],
      "_rank_score": 35
    },
    {
      "id": "36bdddde6420427f9c41e8ec46ea8f5671aa9205",
      "title": "Postgame Pass - Section 107",
      "description": "Postgame Pass - Section 107 at Spectrum Center",
      "start_datetime": "2026-02-10T00:00:00.000Z",
      "end_datetime": null,
      "venue": {
        "name": "Spectrum Center",
        "address": "333 East Trade",
        "neighborhood": "Uptown",
        "lat": 35.22506060000002,
        "lng": -80.8393335
      },
      "category": [
        "special"
      ],
      "price": {
        "min": null,
        "max": null,
        "currency": "USD",
        "notes": "See website"
      },
      "image": "https://s1.ticketm.net/dam/c/8cf/a6653880-7899-4f67-8067-1f95f4d158cf_124761_TABLET_LANDSCAPE_16_9.jpg",
      "source": {
        "name": "Ticketmaster API",
        "url": "https://app.ticketmaster.com/discovery/v2/events",
        "scraped_at": "2026-02-02T15:42:01.511Z"
      },
      "url": "",
      "confidence": 0.9,
      "tags": [
        "ticketmaster-api"
      ],
      "_rank_score": 32
    },
    {
      "id": "e2e1e8c287dad00d6cb625f3f77272345a630abe",
      "title": "Suite Access Pass - Hornets vs. Pistons",
      "description": "Suite Access Pass - Hornets vs. Pistons at Spectrum Center",
      "start_datetime": "2026-02-10T00:00:00.000Z",
      "end_datetime": null,
      "venue": {
        "name": "Spectrum Center",
        "address": "333 E Trade St",
        "neighborhood": "Uptown",
        "lat": 35.225061,
        "lng": -80.839334
      },
      "category": [
        "special"
      ],
      "price": {
        "min": null,
        "max": null,
        "currency": "USD",
        "notes": "See website"
      },
      "image": "https://s1.ticketm.net/dam/c/8cf/a6653880-7899-4f67-8067-1f95f4d158cf_124761_TABLET_LANDSCAPE_16_9.jpg",
      "source": {
        "name": "Ticketmaster API",
        "url": "https://app.ticketmaster.com/discovery/v2/events",
        "scraped_at": "2026-02-02T15:42:01.511Z"
      },
      "url": "",
      "confidence": 0.9,
      "tags": [
        "ticketmaster-api"
      ],
      "_rank_score": 32
    },
    {
      "id": "eb86a4ec5276608c29dfeacd80559445669cbba4",
      "title": "Postgame Pass - Section 103",
      "description": "Postgame Pass - Section 103 at Spectrum Center",
      "start_datetime": "2026-02-10T00:00:00.000Z",
      "end_datetime": null,
      "venue": {
        "name": "Spectrum Center",
        "address": "333 East Trade",
        "neighborhood": "Uptown",
        "lat": 35.22506060000002,
        "lng": -80.8393335
      },
      "category": [
        "special"
      ],
      "price": {
        "min": null,
        "max": null,
        "currency": "USD",
        "notes": "See website"
      },
      "image": "https://s1.ticketm.net/dam/c/8cf/a6653880-7899-4f67-8067-1f95f4d158cf_124761_TABLET_LANDSCAPE_16_9.jpg",
      "source": {
        "name": "Ticketmaster API",
        "url": "https://app.ticketmaster.com/discovery/v2/events",
        "scraped_at": "2026-02-02T15:42:01.511Z"
      },
      "url": "",
      "confidence": 0.9,
      "tags": [
        "ticketmaster-api"
      ],
      "_rank_score": 32
    },
    {
      "id": "d8c768951ee3fbdc3d3894b9604ab1749834dc33",
      "title": "Nine Inch Nails Luxury",
      "description": "Nine Inch Nails Luxury at Spectrum Center",
      "start_datetime": "2026-02-11T01:00:00.000Z",
      "end_datetime": null,
      "venue": {
        "name": "Spectrum Center",
        "address": "333 E Trade St",
        "neighborhood": "Uptown",
        "lat": 35.225061,
        "lng": -80.839334
      },
      "category": [
        "special"
      ],
      "price": {
        "min": null,
        "max": null,
        "currency": "USD",
        "notes": "See website"
      },
      "image": "https://s1.ticketm.net/dam/c/8cf/a6653880-7899-4f67-8067-1f95f4d158cf_124761_TABLET_LANDSCAPE_16_9.jpg",
      "source": {
        "name": "Ticketmaster API",
        "url": "https://app.ticketmaster.com/discovery/v2/events",
        "scraped_at": "2026-02-02T15:42:01.512Z"
      },
      "url": "",
      "confidence": 0.9,
      "tags": [
        "ticketmaster-api"
      ],
      "_rank_score": 32
    },
    {
      "id": "c353bdeddbacd3e8e50b0c49a3d001e7abd4465e",
      "title": "Postgame Pass - Section 107",
      "description": "Postgame Pass - Section 107 at Spectrum Center",
      "start_datetime": "2026-02-12T00:00:00.000Z",
      "end_datetime": null,
      "venue": {
        "name": "Spectrum Center",
        "address": "333 East Trade",
        "neighborhood": "Uptown",
        "lat": 35.22506060000002,
        "lng": -80.8393335
      },
      "category": [
        "special"
      ],
      "price": {
        "min": null,
        "max": null,
        "currency": "USD",
        "notes": "See website"
      },
      "image": "https://s1.ticketm.net/dam/c/8cf/a6653880-7899-4f67-8067-1f95f4d158cf_124761_TABLET_LANDSCAPE_16_9.jpg",
      "source": {
        "name": "Ticketmaster API",
        "url": "https://app.ticketmaster.com/discovery/v2/events",
        "scraped_at": "2026-02-02T15:42:01.512Z"
      },
      "url": "",
      "confidence": 0.9,
      "tags": [
        "ticketmaster-api"
      ],
      "_rank_score": 32
    },
    {
      "id": "16ed388bbe5275545e5a4c58a098a869b0daa622",
      "title": "Postgame Pass - Section 103",
      "description": "Postgame Pass - Section 103 at Spectrum Center",
      "start_datetime": "2026-02-12T00:00:00.000Z",
      "end_datetime": null,
      "venue": {
        "name": "Spectrum Center",
        "address": "333 East Trade",
        "neighborhood": "Uptown",
        "lat": 35.22506060000002,
        "lng": -80.8393335
      },
      "category": [
        "special"
      ],
      "price": {
        "min": null,
        "max": null,
        "currency": "USD",
        "notes": "See website"
      },
      "image": "https://s1.ticketm.net/dam/c/8cf/a6653880-7899-4f67-8067-1f95f4d158cf_124761_TABLET_LANDSCAPE_16_9.jpg",
      "source": {
        "name": "Ticketmaster API",
        "url": "https://app.ticketmaster.com/discovery/v2/events",
        "scraped_at": "2026-02-02T15:42:01.512Z"
      },
      "url": "",
      "confidence": 0.9,
      "tags": [
        "ticketmaster-api"
      ],
      "_rank_score": 32
    },
    {
      "id": "933f3e33ebb2a96854d80b74ae7cfe0a2c125119",
      "title": "Suite Access Pass - Hornets vs. Hawks",
      "description": "Suite Access Pass - Hornets vs. Hawks at Spectrum Center",
      "start_datetime": "2026-02-12T00:00:00.000Z",
      "end_datetime": null,
      "venue": {
        "name": "Spectrum Center",
        "address": "333 E Trade St",
        "neighborhood": "Uptown",
        "lat": 35.225061,
        "lng": -80.839334
      },
      "category": [
        "special"
      ],
      "price": {
        "min": null,
        "max": null,
        "currency": "USD",
        "notes": "See website"
      },
      "image": "https://s1.ticketm.net/dam/c/8cf/a6653880-7899-4f67-8067-1f95f4d158cf_124761_TABLET_LANDSCAPE_16_9.jpg",
      "source": {
        "name": "Ticketmaster API",
        "url": "https://app.ticketmaster.com/discovery/v2/events",
        "scraped_at": "2026-02-02T15:42:01.512Z"
      },
      "url": "",
      "confidence": 0.9,
      "tags": [
        "ticketmaster-api"
      ],
      "_rank_score": 32
    },
    {
      "id": "39238253ee1a203af6878b99bcda60f228430ff6",
      "title": "18 Great Day Trips from Charlotte",
      "description": "",
      "start_datetime": null,
      "end_datetime": null,
      "venue": {
        "name": "Day Trips from Charlotte",
        "address": "",
        "neighborhood": "",
        "lat": null,
        "lng": null
      },
      "category": [
        "special"
      ],
      "price": {
        "min": null,
        "max": null,
        "currency": "USD",
        "notes": "Check for low-cost options"
      },
      "image": "https://www.charlotteonthecheap.com/lotc-cms/wp-content/uploads/2017/07/hiddenite-emarld-hollow-2-150x150.jpg",
      "source": {
        "name": "Charlotte on the Cheap",
        "url": "https://www.charlotteonthecheap.com/",
        "scraped_at": "2026-02-02T15:42:01.513Z"
      },
      "url": "https://www.charlotteonthecheap.com/frugal-family-day-trips-charlotte/",
      "confidence": 0.5499999999999999,
      "tags": [
        "cheap",
        "budget-friendly"
      ],
      "_rank_score": 1.4999999999999964
    },
    {
      "id": "dbdaf3fe3f87815243401adaec15f3a9d50c67d2",
      "title": "Free days at Charlotte museums",
      "description": "",
      "start_datetime": null,
      "end_datetime": null,
      "venue": {
        "name": "Charlotte museums",
        "address": "",
        "neighborhood": "",
        "lat": null,
        "lng": null
      },
      "category": [
        "special"
      ],
      "price": {
        "min": null,
        "max": null,
        "currency": "USD",
        "notes": "Free"
      },
      "image": "https://www.charlotteonthecheap.com/lotc-cms/wp-content/uploads/2021/03/bechtler-firebird-150x150.jpg",
      "source": {
        "name": "Charlotte on the Cheap",
        "url": "https://www.charlotteonthecheap.com/",
        "scraped_at": "2026-02-02T15:42:01.513Z"
      },
      "url": "https://www.charlotteonthecheap.com/free-days-at-charlotte-museums/",
      "confidence": 0.5499999999999999,
      "tags": [
        "cheap",
        "budget-friendly"
      ],
      "_rank_score": 1.4999999999999964
    },
    {
      "id": "717566e87fc4f77a2ea51a459cd1c142f0943f07",
      "title": "Free and cheap things to do in Charlotte this week",
      "description": "",
      "start_datetime": null,
      "end_datetime": null,
      "venue": {
        "name": "",
        "address": "",
        "neighborhood": "",
        "lat": null,
        "lng": null
      },
      "category": [
        "special"
      ],
      "price": {
        "min": null,
        "max": null,
        "currency": "USD",
        "notes": "Free"
      },
      "image": "https://www.charlotteonthecheap.com/lotc-cms/wp-content/uploads/2025/06/Free-things-to-do-this-week-charlotte-150x150.jpg",
      "source": {
        "name": "Charlotte on the Cheap",
        "url": "https://www.charlotteonthecheap.com/",
        "scraped_at": "2026-02-02T15:42:01.513Z"
      },
      "url": "https://www.charlotteonthecheap.com/freethingstodo/",
      "confidence": 0.4,
      "tags": [
        "cheap",
        "budget-friendly"
      ],
      "_rank_score": -3
    },
    {
      "id": "e8a4f429d5cf7ac8512fba741c62e4d5e4288373",
      "title": "Free and cheap things to do in Charlotte this weekend",
      "description": "",
      "start_datetime": null,
      "end_datetime": null,
      "venue": {
        "name": "",
        "address": "",
        "neighborhood": "",
        "lat": null,
        "lng": null
      },
      "category": [
        "special"
      ],
      "price": {
        "min": null,
        "max": null,
        "currency": "USD",
        "notes": "Free"
      },
      "image": "https://www.charlotteonthecheap.com/lotc-cms/wp-content/uploads/2025/05/free-and-cheap-things-weekend-charlotte-150x150.jpg",
      "source": {
        "name": "Charlotte on the Cheap",
        "url": "https://www.charlotteonthecheap.com/",
        "scraped_at": "2026-02-02T15:42:01.513Z"
      },
      "url": "https://www.charlotteonthecheap.com/free-things-weekend-4/",
      "confidence": 0.4,
      "tags": [
        "cheap",
        "budget-friendly"
      ],
      "_rank_score": -3
    },
    {
      "id": "9320ef44b0e64221668da1ba49ed7c19c3da54ce",
      "title": "50+ Cheap Dates in Charlotte",
      "description": "",
      "start_datetime": null,
      "end_datetime": null,
      "venue": {
        "name": "",
        "address": "",
        "neighborhood": "",
        "lat": null,
        "lng": null
      },
      "category": [
        "special"
      ],
      "price": {
        "min": null,
        "max": null,
        "currency": "USD",
        "notes": "Check for low-cost options"
      },
      "image": "https://www.charlotteonthecheap.com/lotc-cms/wp-content/uploads/2023/01/rosies-wine-garden-jlm-150x150.jpg",
      "source": {
        "name": "Charlotte on the Cheap",
        "url": "https://www.charlotteonthecheap.com/",
        "scraped_at": "2026-02-02T15:42:01.513Z"
      },
      "url": "https://www.charlotteonthecheap.com/cheap-dates/",
      "confidence": 0.4,
      "tags": [
        "cheap",
        "budget-friendly"
      ],
      "_rank_score": -3
    },
    {
      "id": "5244967c62717b7bccad9b095a560677c3141e85",
      "title": "Free fitness classes and events in Charlotte  a calendar",
      "description": "",
      "start_datetime": null,
      "end_datetime": null,
      "venue": {
        "name": "",
        "address": "",
        "neighborhood": "",
        "lat": null,
        "lng": null
      },
      "category": [
        "special"
      ],
      "price": {
        "min": null,
        "max": null,
        "currency": "USD",
        "notes": "Free"
      },
      "image": "https://www.charlotteonthecheap.com/lotc-cms/wp-content/uploads/2019/03/charlotte-on-the-cheap-fitness-150x150.jpg",
      "source": {
        "name": "Charlotte on the Cheap",
        "url": "https://www.charlotteonthecheap.com/",
        "scraped_at": "2026-02-02T15:42:01.513Z"
      },
      "url": "https://www.charlotteonthecheap.com/free-fitness-classes-charlotte/",
      "confidence": 0.4,
      "tags": [
        "cheap",
        "budget-friendly"
      ],
      "_rank_score": -3
    },
    {
      "id": "c343d65e9b9692ad15f0fced4b928f1fd5d9ffe0",
      "title": "9 Spring Consignment Sales in Charlotte 2026",
      "description": "",
      "start_datetime": null,
      "end_datetime": null,
      "venue": {
        "name": "",
        "address": "",
        "neighborhood": "",
        "lat": null,
        "lng": null
      },
      "category": [
        "special"
      ],
      "price": {
        "min": null,
        "max": null,
        "currency": "USD",
        "notes": "Check for low-cost options"
      },
      "image": "https://www.charlotteonthecheap.com/lotc-cms/wp-content/uploads/2026/01/spring-consignment-sales-150x150.jpg",
      "source": {
        "name": "Charlotte on the Cheap",
        "url": "https://www.charlotteonthecheap.com/",
        "scraped_at": "2026-02-02T15:42:01.513Z"
      },
      "url": "https://www.charlotteonthecheap.com/charlotte-spring-consignment-sales/",
      "confidence": 0.4,
      "tags": [
        "cheap",
        "budget-friendly"
      ],
      "_rank_score": -3
    },
    {
      "id": "aa5bbccffa1f9dae47fc4d065190c3eb74f83593",
      "title": "120 Charlotte area thrift, consignment, used books, antique and vintage stores",
      "description": "",
      "start_datetime": null,
      "end_datetime": null,
      "venue": {
        "name": "",
        "address": "",
        "neighborhood": "",
        "lat": null,
        "lng": null
      },
      "category": [
        "special"
      ],
      "price": {
        "min": null,
        "max": null,
        "currency": "USD",
        "notes": "Check for low-cost options"
      },
      "image": "https://www.charlotteonthecheap.com/lotc-cms/wp-content/uploads/2023/02/remix-market-harrisburg-jlm-150x150.jpg",
      "source": {
        "name": "Charlotte on the Cheap",
        "url": "https://www.charlotteonthecheap.com/",
        "scraped_at": "2026-02-02T15:42:01.513Z"
      },
      "url": "https://www.charlotteonthecheap.com/charlotte-area-thrift-consignment-vintage-store/",
      "confidence": 0.4,
      "tags": [
        "cheap",
        "budget-friendly"
      ],
      "_rank_score": -3
    },
    {
      "id": "e6d6f5c111afa79a5066ed5441b2b19008a99098",
      "title": "Day-by-day list of markets around Charlotte  art, vintage, hand-made items",
      "description": "",
      "start_datetime": null,
      "end_datetime": null,
      "venue": {
        "name": "",
        "address": "",
        "neighborhood": "",
        "lat": null,
        "lng": null
      },
      "category": [
        "special"
      ],
      "price": {
        "min": null,
        "max": null,
        "currency": "USD",
        "notes": "Check for low-cost options"
      },
      "image": "https://www.charlotteonthecheap.com/lotc-cms/wp-content/uploads/2023/09/ceramic-cups-Depositphotos_213916864_S-150x150.jpeg",
      "source": {
        "name": "Charlotte on the Cheap",
        "url": "https://www.charlotteonthecheap.com/",
        "scraped_at": "2026-02-02T15:42:01.513Z"
      },
      "url": "https://www.charlotteonthecheap.com/markets/",
      "confidence": 0.4,
      "tags": [
        "cheap",
        "budget-friendly"
      ],
      "_rank_score": -3
    },
    {
      "id": "0e1c37991a06b609dcdd2ee6d52a6b966306c6ad",
      "title": "Charlotte Garage Sales this weekend  and 10 hints for finding hidden gems at great prices",
      "description": "",
      "start_datetime": null,
      "end_datetime": null,
      "venue": {
        "name": "",
        "address": "",
        "neighborhood": "",
        "lat": null,
        "lng": null
      },
      "category": [
        "special"
      ],
      "price": {
        "min": null,
        "max": null,
        "currency": "USD",
        "notes": "Check for low-cost options"
      },
      "image": "https://www.charlotteonthecheap.com/lotc-cms/wp-content/uploads/2019/07/garage-sale-Depositphotos_17860049_s-2019-150x150.jpg",
      "source": {
        "name": "Charlotte on the Cheap",
        "url": "https://www.charlotteonthecheap.com/",
        "scraped_at": "2026-02-02T15:42:01.513Z"
      },
      "url": "https://www.charlotteonthecheap.com/charlotte-garage-sales/",
      "confidence": 0.4,
      "tags": [
        "cheap",
        "budget-friendly"
      ],
      "_rank_score": -3
    },
    {
      "id": "4a50fb93b86d860da3927d2360ce634af47df458",
      "title": "Queen's Feast: Winter Edition",
      "description": "",
      "start_datetime": null,
      "end_datetime": null,
      "venue": {
        "name": "",
        "address": "",
        "neighborhood": "",
        "lat": null,
        "lng": null
      },
      "category": [
        "special"
      ],
      "price": {
        "min": null,
        "max": null,
        "currency": "USD",
        "notes": ""
      },
      "image": null,
      "source": {
        "name": "Visit Charlotte",
        "url": "https://www.charlottesgotalot.com/events",
        "scraped_at": "2026-02-02T15:42:01.512Z"
      },
      "url": "https://www.charlottesgotalot.com/events",
      "confidence": 0.30000000000000004,
      "tags": [],
      "_rank_score": -5.999999999999998
    },
    {
      "id": "c16dba62222bb87550030d28ee9daee441e2cdbd",
      "title": "Mid Atlantic Boat Show - Consumer Show",
      "description": "",
      "start_datetime": null,
      "end_datetime": null,
      "venue": {
        "name": "",
        "address": "",
        "neighborhood": "",
        "lat": null,
        "lng": null
      },
      "category": [
        "special"
      ],
      "price": {
        "min": null,
        "max": null,
        "currency": "USD",
        "notes": ""
      },
      "image": null,
      "source": {
        "name": "Visit Charlotte",
        "url": "https://www.charlottesgotalot.com/events",
        "scraped_at": "2026-02-02T15:42:01.512Z"
      },
      "url": "https://www.charlottesgotalot.com/events",
      "confidence": 0.30000000000000004,
      "tags": [],
      "_rank_score": -5.999999999999998
    },
    {
      "id": "ddd872ac656e518a7397bbed1162028ce9ff1a4a",
      "title": "Dog Days of Winter Dog Jog",
      "description": "",
      "start_datetime": null,
      "end_datetime": null,
      "venue": {
        "name": "",
        "address": "",
        "neighborhood": "",
        "lat": null,
        "lng": null
      },
      "category": [
        "special"
      ],
      "price": {
        "min": null,
        "max": null,
        "currency": "USD",
        "notes": ""
      },
      "image": null,
      "source": {
        "name": "Visit Charlotte",
        "url": "https://www.charlottesgotalot.com/events",
        "scraped_at": "2026-02-02T15:42:01.512Z"
      },
      "url": "https://www.charlottesgotalot.com/events",
      "confidence": 0.30000000000000004,
      "tags": [],
      "_rank_score": -5.999999999999998
    },
    {
      "id": "f8516d083e92421844279ab23e1f6eedf212bdb8",
      "title": "Dog Days of Winter",
      "description": "",
      "start_datetime": null,
      "end_datetime": null,
      "venue": {
        "name": "",
        "address": "",
        "neighborhood": "",
        "lat": null,
        "lng": null
      },
      "category": [
        "special"
      ],
      "price": {
        "min": null,
        "max": null,
        "currency": "USD",
        "notes": ""
      },
      "image": null,
      "source": {
        "name": "Visit Charlotte",
        "url": "https://www.charlottesgotalot.com/events",
        "scraped_at": "2026-02-02T15:42:01.512Z"
      },
      "url": "https://www.charlottesgotalot.com/events",
      "confidence": 0.30000000000000004,
      "tags": [],
      "_rank_score": -5.999999999999998
    }
  ]
}